Workbook

Sheet Início
B2: Planilha de orçamento e plano financeiro
B3: Complemento do livro "Dinheiro: Querer, poder e gastar", de Flávio Lemos, CMT, CFP® (Apêndice A) · ARQUIVO DE EXEMPLO: Paula e Marcos, cap. 35
B5: Ano do orçamento | C5: 2026
B6: Nome da pessoa 1 | C6: Paula
B7: Nome da pessoa 2 (se houver) | C7: Marcos
B9: Como usar, na ordem das 6 etapas do cap. 35
B10: 1. Combine as regras | C10: Aba Plano: quem participa, dia da revisão mensal, mês da revisão anual e a divisão das contas do casal.
B11: 2. Faça o retrato | C11: Abas Jan a Dez: lance três meses de extratos e faturas. Aba Irregulares: despesas que não vêm todo mês. Abas Patrimônio e Dívidas: o que você tem e o que deve.
B12: 3. Faça o diagnóstico | C12: Aba Resumo: margem, taxa de poupança e divisão dos gastos. Aba Patrimônio: meses de reserva. Aba Dívidas: ordem de quitação.
B13: 4. Escreva o plano | C13: Aba Metas: finalidade, valor e data de cada objetivo e o depósito mensal necessário. Aba Plano: o plano em uma página.
B14: 5. Coloque em prática | C14: Na seção "Destino da margem" de cada mês, registre o que foi para dívidas, reserva, metas e aposentadoria.
B15: 6. Acompanhe e revise | C15: Uma hora por mês: compare previsto e realizado. Uma vez por ano: aba Revisão.
B17: Legenda das cores
B18: Exemplo | C18: Amarelo com texto azul: digite aqui.
B19: Exemplo | C19: Verde: vem do mês anterior ou de outra aba; pode digitar por cima se o valor mudar.
B20: Exemplo | C20: Cinza ou texto preto: conta automática; não apague.
B22: Calculadoras do blog (cada uma faz uma conta específica)
B23: Roteiro: planejamento em 6 etapas | C23: https://www.traderbrasil.com/blog/planejamento-financeiro-como-organizar-seu-dinheiro.php
B24: Orçamento 50/30/20 e margem mensal | C24: https://www.traderbrasil.com/blog/calculadora-orcamento-50-30-20-margem-mensal.php
B25: Quitar dívidas: bola de neve x avalanche | C25: https://www.traderbrasil.com/blog/calculadora-quitar-dividas-bola-de-neve-avalanche.php
B26: Parcelado ou à vista | C26: https://www.traderbrasil.com/blog/calculadora-parcelado-ou-a-vista.php
B27: Reserva de emergência | C27: https://www.traderbrasil.com/blog/calculadora-reserva-de-emergencia.php
B28: Meta financeira: quanto guardar por mês | C28: https://www.traderbrasil.com/blog/calculadora-meta-financeira-quanto-guardar-por-mes.php
B29: Inflação (IPCA) e poder de compra | C29: https://www.traderbrasil.com/blog/calculadora-inflacao-ipca-poder-de-compra.php
B30: Aposentadoria: quanto preciso acumular | C30: https://www.traderbrasil.com/blog/calculadora-de-aposentadoria-quanto-preciso-acumular.php
B31: Imposto de renda 2026 | C31: https://www.traderbrasil.com/blog/calculadora-imposto-de-renda-2026-isencao-5-mil.php
B32: Patrimônio da família e do negócio | C32: https://www.traderbrasil.com/blog/como-organizar-o-patrimonio-da-familia-e-do-negocio.php
B33: Os números do ano | C33: https://www.traderbrasil.com/blog/os-numeros-do-ano-financas-2026.php
B35: Privacidade | C35: Esta planilha fica só no seu computador ou na sua conta. Não coloque senhas, números de conta ou de cartão.
... B37: Versão | C37: Outubro de 2026

Sheet Plano
B2: Meu plano em uma página
B3: Se não cabe numa página, está complicado demais para ser seguido (cap. 35).
B5: ETAPA 1. REGRAS COMBINADAS
B6: Quem participa do plano | C6: Paula e Marcos
B7: Dia do mês para acompanhar (uma hora) | C7: Primeiro domingo
B8: Mês da revisão anual | C8: Janeiro
B9: Ajuda profissional? (sozinho, planejador, consultor) | C9: Sozinhos por enquanto
B10: Regra de honestidade | C10: Todos os números na mesa, inclusive os feios
B11: Data da próxima revisão | C11: 46397
B13: A ORDEM DO DINHEIRO | C13: Situação | D13: Próximo passo
B14: 1. Contas essenciais em dia | C14: Feito
B15: 2. Fim das dívidas caras (cap. 24) | C15: Feito | D15: Rotativo quitado com a poupança
B16: 3. Reserva de emergência (cap. 8) | C16: Em andamento | D16: R$ 1.000 por mês até 3 meses de gastos
B17: 4. Proteção: seguros (cap. 20) | C17: Em andamento | D17: Seguro de vida temporário contratado
B18: 5. Objetivos com data (caps. 2, 25, 26) | C18: Em andamento | D18: Entrada do apartamento: R$ 480 por mês
B19: 6. Aposentadoria (caps. 31 e 32) | C19: Pendente | D19: Rever depois da compra do apartamento
B20: 7. Impostos e legado (caps. 33 e 34) | C20: Pendente | D20: Testamento e beneficiários
B22: METAS (vêm da aba Metas) | C22: Depósito planejado | D22: Valor, data e onde guardar
B23: =IF(Metas!B6="","",Metas!B6) -> Entrada do apartamento | C23: =IF(Metas!B6="","",Metas!I6) -> 480 | D23: =IF(Metas!B6="","","R$ "&FIXED(Metas!C6,0)&" até "&RIGHT("0"&MONTH(Metas!D6),2)&"/"&YEAR(Metas!D6)&"; "&Metas!K6) -> R$ 80,000 até 12/2030; Vencimento perto da data da compra
B24: =IF(Metas!B7="","",Metas!B7) -> Faculdade do filho | C24: =IF(Metas!B7="","",Metas!I7) -> 0 | D24: =IF(Metas!B7="","","R$ "&FIXED(Metas!C7,0)&" até "&RIGHT("0"&MONTH(Metas!D7),2)&"/"&YEAR(Metas!D7)&"; "&Metas!K7) -> R$ 100,000 até 01/2040; Longo prazo, conforme o perfil
B25: =IF(Metas!B8="","",Metas!B8) | C25: =IF(Metas!B8="","",Metas!I8) | D25: =IF(Metas!B8="","","R$ "&FIXED(Metas!C8,0)&" até "&RIGHT("0"&MONTH(Metas!D8),2)&"/"&YEAR(Metas!D8)&"; "&Metas!K8)
B26: =IF(Metas!B9="","",Metas!B9) | C26: =IF(Metas!B9="","",Metas!I9) | D26: =IF(Metas!B9="","","R$ "&FIXED(Metas!C9,0)&" até "&RIGHT("0"&MONTH(Metas!D9),2)&"/"&YEAR(Metas!D9)&"; "&Metas!K9)
B27: =IF(Metas!B10="","",Metas!B10) | C27: =IF(Metas!B10="","",Metas!I10) | D27: =IF(Metas!B10="","","R$ "&FIXED(Metas!C10,0)&" até "&RIGHT("0"&MONTH(Metas!D10),2)&"/"&YEAR(Metas!D10)&"; "&Metas!K10)
B28: Total planejado para as metas | C28: =Metas!I12 -> 480
B29: Margem média para o plano (aba Resumo) | C29: =Resumo!O15 -> 1606.6667
B31: O QUE FICOU PARA DEPOIS (e por quê)
B32: Faculdade e aposentadoria recebem mais depois da compra do apartamento, ou antes se a renda subir.

Sheet Resumo
A1: ="Resumo do ano de "&Início!$C$5&" (valores realizados)" -> Resumo do ano de 2026 (valores realizados)
A2: Preenche sozinho a partir das abas dos meses. A média considera só os meses com valor.
A4: Linha | B4: Jan | C4: Fev | D4: Mar | E4: Abr | F4: Mai | G4: Jun | H4: Jul | I4: Ago | J4: Set | K4: Out | L4: Nov | M4: Dez | N4: Total | O4: Média
A5: ="Renda líquida de "&Início!$C$6 -> Renda líquida de Paula | B5: =N(Jan!C5) -> 4500 | C5: =N(Fev!C5) -> 4500 | D5: =N(Mar!C5) -> 4500 | E5: =N(Abr!C5) -> 0 | F5: =N(Mai!C5) -> 0 | G5: =N(Jun!C5) -> 0 | H5: =N(Jul!C5) -> 0 | I5: =N(Ago!C5) -> 0 | J5: =N(Set!C5) -> 0 | K5: =N(Out!C5) -> 0 | L5: =N(Nov!C5) -> 0 | M5: =N(Dez!C5) -> 0 | N5: =SUM(B5:M5) -> 13500 | O5: =IFERROR(AVERAGEIF(B5:M5,"<>0"),0) -> 4500
A6: ="Renda líquida de "&Início!$C$7 -> Renda líquida de Marcos | B6: =N(Jan!C6) -> 3500 | C6: =N(Fev!C6) -> 3500 | D6: =N(Mar!C6) -> 3500 | E6: =N(Abr!C6) -> 0 | F6: =N(Mai!C6) -> 0 | G6: =N(Jun!C6) -> 0 | H6: =N(Jul!C6) -> 0 | I6: =N(Ago!C6) -> 0 | J6: =N(Set!C6) -> 0 | K6: =N(Out!C6) -> 0 | L6: =N(Nov!C6) -> 0 | M6: =N(Dez!C6) -> 0 | N6: =SUM(B6:M6) -> 10500 | O6: =IFERROR(AVERAGEIF(B6:M6,"<>0"),0) -> 3500
A7: Renda recorrente | B7: =N(Jan!C8) -> 8000 | C7: =N(Fev!C8) -> 8000 | D7: =N(Mar!C8) -> 8000 | E7: =N(Abr!C8) -> 0 | F7: =N(Mai!C8) -> 0 | G7: =N(Jun!C8) -> 0 | H7: =N(Jul!C8) -> 0 | I7: =N(Ago!C8) -> 0 | J7: =N(Set!C8) -> 0 | K7: =N(Out!C8) -> 0 | L7: =N(Nov!C8) -> 0 | M7: =N(Dez!C8) -> 0 | N7: =SUM(B7:M7) -> 24000 | O7: =IFERROR(AVERAGEIF(B7:M7,"<>0"),0) -> 8000
A8: Renda total | B8: =N(Jan!C10) -> 8000 | C8: =N(Fev!C10) -> 8000 | D8: =N(Mar!C10) -> 8000 | E8: =N(Abr!C10) -> 0 | F8: =N(Mai!C10) -> 0 | G8: =N(Jun!C10) -> 0 | H8: =N(Jul!C10) -> 0 | I8: =N(Ago!C10) -> 0 | J8: =N(Set!C10) -> 0 | K8: =N(Out!C10) -> 0 | L8: =N(Nov!C10) -> 0 | M8: =N(Dez!C10) -> 0 | N8: =SUM(B8:M8) -> 24000 | O8: =IFERROR(AVERAGEIF(B8:M8,"<>0"),0) -> 8000
A9: Essenciais | B9: =N(Jan!C19) -> 4170 | C9: =N(Fev!C19) -> 4170 | D9: =N(Mar!C19) -> 4220 | E9: =N(Abr!C19) -> 0 | F9: =N(Mai!C19) -> 0 | G9: =N(Jun!C19) -> 0 | H9: =N(Jul!C19) -> 0 | I9: =N(Ago!C19) -> 0 | J9: =N(Set!C19) -> 0 | K9: =N(Out!C19) -> 0 | L9: =N(Nov!C19) -> 0 | M9: =N(Dez!C19) -> 0 | N9: =SUM(B9:M9) -> 12560 | O9: =IFERROR(AVERAGEIF(B9:M9,"<>0"),0) -> 4186.6667
A10: Compromissos | B10: =N(Jan!C27) -> 1300 | C10: =N(Fev!C27) -> 1300 | D10: =N(Mar!C27) -> 1300 | E10: =N(Abr!C27) -> 0 | F10: =N(Mai!C27) -> 0 | G10: =N(Jun!C27) -> 0 | H10: =N(Jul!C27) -> 0 | I10: =N(Ago!C27) -> 0 | J10: =N(Set!C27) -> 0 | K10: =N(Out!C27) -> 0 | L10: =N(Nov!C27) -> 0 | M10: =N(Dez!C27) -> 0 | N10: =SUM(B10:M10) -> 3900 | O10: =IFERROR(AVERAGEIF(B10:M10,"<>0"),0) -> 1300
A11: Provisão de irregulares | B11: =N(Jan!C30) -> 500 | C11: =N(Fev!C30) -> 500 | D11: =N(Mar!C30) -> 500 | E11: =N(Abr!C30) -> 0 | F11: =N(Mai!C30) -> 0 | G11: =N(Jun!C30) -> 0 | H11: =N(Jul!C30) -> 0 | I11: =N(Ago!C30) -> 0 | J11: =N(Set!C30) -> 0 | K11: =N(Out!C30) -> 0 | L11: =N(Nov!C30) -> 0 | M11: =N(Dez!C30) -> 0 | N11: =SUM(B11:M11) -> 1500 | O11: =IFERROR(AVERAGEIF(B11:M11,"<>0"),0) -> 500
A12: Irregulares pagas | B12: =N(Jan!C31) -> 1800 | C12: =N(Fev!C31) -> 600 | D12: =N(Mar!C31) -> 2400 | E12: =N(Abr!C31) -> 0 | F12: =N(Mai!C31) -> 0 | G12: =N(Jun!C31) -> 0 | H12: =N(Jul!C31) -> 0 | I12: =N(Ago!C31) -> 0 | J12: =N(Set!C31) -> 0 | K12: =N(Out!C31) -> 0 | L12: =N(Nov!C31) -> 0 | M12: =N(Dez!C31) -> 0 | N12: =SUM(B12:M12) -> 4800 | O12: =IFERROR(AVERAGEIF(B12:M12,"<>0"),0) -> 1600
A13: Margem de decisão | B13: =N(Jan!C33) -> 2030 | C13: =N(Fev!C33) -> 2030 | D13: =N(Mar!C33) -> 1980 | E13: =N(Abr!C33) -> 0 | F13: =N(Mai!C33) -> 0 | G13: =N(Jun!C33) -> 0 | H13: =N(Jul!C33) -> 0 | I13: =N(Ago!C33) -> 0 | J13: =N(Set!C33) -> 0 | K13: =N(Out!C33) -> 0 | L13: =N(Nov!C33) -> 0 | M13: =N(Dez!C33) -> 0 | N13: =SUM(B13:M13) -> 6040 | O13: =IFERROR(AVERAGEIF(B13:M13,"<>0"),0) -> 2013.3333
A14: Flexíveis | B14: =N(Jan!C42) -> 410 | C14: =N(Fev!C42) -> 340 | D14: =N(Mar!C42) -> 470 | E14: =N(Abr!C42) -> 0 | F14: =N(Mai!C42) -> 0 | G14: =N(Jun!C42) -> 0 | H14: =N(Jul!C42) -> 0 | I14: =N(Ago!C42) -> 0 | J14: =N(Set!C42) -> 0 | K14: =N(Out!C42) -> 0 | L14: =N(Nov!C42) -> 0 | M14: =N(Dez!C42) -> 0 | N14: =SUM(B14:M14) -> 1220 | O14: =IFERROR(AVERAGEIF(B14:M14,"<>0"),0) -> 406.66667
A15: Margem para o plano | B15: =N(Jan!C43) -> 1620 | C15: =N(Fev!C43) -> 1690 | D15: =N(Mar!C43) -> 1510 | E15: =N(Abr!C43) -> 0 | F15: =N(Mai!C43) -> 0 | G15: =N(Jun!C43) -> 0 | H15: =N(Jul!C43) -> 0 | I15: =N(Ago!C43) -> 0 | J15: =N(Set!C43) -> 0 | K15: =N(Out!C43) -> 0 | L15: =N(Nov!C43) -> 0 | M15: =N(Dez!C43) -> 0 | N15: =SUM(B15:M15) -> 4820 | O15: =IFERROR(AVERAGEIF(B15:M15,"<>0"),0) -> 1606.6667
A16: Total do plano | B16: =N(Jan!C55) -> 1600 | C16: =N(Fev!C55) -> 1600 | D16: =N(Mar!C55) -> 1600 | E16: =N(Abr!C55) -> 0 | F16: =N(Mai!C55) -> 0 | G16: =N(Jun!C55) -> 0 | H16: =N(Jul!C55) -> 0 | I16: =N(Ago!C55) -> 0 | J16: =N(Set!C55) -> 0 | K16: =N(Out!C55) -> 0 | L16: =N(Nov!C55) -> 0 | M16: =N(Dez!C55) -> 0 | N16: =SUM(B16:M16) -> 4800 | O16: =IFERROR(AVERAGEIF(B16:M16,"<>0"),0) -> 1600
A17: Saldo do mês | B17: =N(Jan!C57) -> 20 | C17: =N(Fev!C57) -> 90 | D17: =N(Mar!C57) -> -90 | E17: =N(Abr!C57) -> 0 | F17: =N(Mai!C57) -> 0 | G17: =N(Jun!C57) -> 0 | H17: =N(Jul!C57) -> 0 | I17: =N(Ago!C57) -> 0 | J17: =N(Set!C57) -> 0 | K17: =N(Out!C57) -> 0 | L17: =N(Nov!C57) -> 0 | M17: =N(Dez!C57) -> 0 | N17: =SUM(B17:M17) -> 20 | O17: =IFERROR(AVERAGEIF(B17:M17,"<>0"),0) -> 6.6666667
A18: Do plano: dívidas caras | B18: =N(Jan!C46) -> 0 | C18: =N(Fev!C46) -> 0 | D18: =N(Mar!C46) -> 0 | E18: =N(Abr!C46) -> 0 | F18: =N(Mai!C46) -> 0 | G18: =N(Jun!C46) -> 0 | H18: =N(Jul!C46) -> 0 | I18: =N(Ago!C46) -> 0 | J18: =N(Set!C46) -> 0 | K18: =N(Out!C46) -> 0 | L18: =N(Nov!C46) -> 0 | M18: =N(Dez!C46) -> 0 | N18: =SUM(B18:M18) -> 0 | O18: =IFERROR(AVERAGEIF(B18:M18,"<>0"),0) -> 0
A19: Do plano: reserva de emergência | B19: =N(Jan!C47) -> 1000 | C19: =N(Fev!C47) -> 1000 | D19: =N(Mar!C47) -> 1000 | E19: =N(Abr!C47) -> 0 | F19: =N(Mai!C47) -> 0 | G19: =N(Jun!C47) -> 0 | H19: =N(Jul!C47) -> 0 | I19: =N(Ago!C47) -> 0 | J19: =N(Set!C47) -> 0 | K19: =N(Out!C47) -> 0 | L19: =N(Nov!C47) -> 0 | M19: =N(Dez!C47) -> 0 | N19: =SUM(B19:M19) -> 3000 | O19: =IFERROR(AVERAGEIF(B19:M19,"<>0"),0) -> 1000
A20: Do plano: seguro e proteção | B20: =N(Jan!C48) -> 120 | C20: =N(Fev!C48) -> 120 | D20: =N(Mar!C48) -> 120 | E20: =N(Abr!C48) -> 0 | F20: =N(Mai!C48) -> 0 | G20: =N(Jun!C48) -> 0 | H20: =N(Jul!C48) -> 0 | I20: =N(Ago!C48) -> 0 | J20: =N(Set!C48) -> 0 | K20: =N(Out!C48) -> 0 | L20: =N(Nov!C48) -> 0 | M20: =N(Dez!C48) -> 0 | N20: =SUM(B20:M20) -> 360 | O20: =IFERROR(AVERAGEIF(B20:M20,"<>0"),0) -> 120
A21: Do plano: aposentadoria | B21: =N(Jan!C54) -> 0 | C21: =N(Fev!C54) -> 0 | D21: =N(Mar!C54) -> 0 | E21: =N(Abr!C54) -> 0 | F21: =N(Mai!C54) -> 0 | G21: =N(Jun!C54) -> 0 | H21: =N(Jul!C54) -> 0 | I21: =N(Ago!C54) -> 0 | J21: =N(Set!C54) -> 0 | K21: =N(Out!C54) -> 0 | L21: =N(Nov!C54) -> 0 | M21: =N(Dez!C54) -> 0 | N21: =SUM(B21:M21) -> 0 | O21: =IFERROR(AVERAGEIF(B21:M21,"<>0"),0) -> 0
A22: Gastos do mês | B22: =B9+B10+B14+B12 -> 7680 | C22: =C9+C10+C14+C12 -> 6410 | D22: =D9+D10+D14+D12 -> 8390 | E22: =E9+E10+E14+E12 -> 0 | F22: =F9+F10+F14+F12 -> 0 | G22: =G9+G10+G14+G12 -> 0 | H22: =H9+H10+H14+H12 -> 0 | I22: =I9+I10+I14+I12 -> 0 | ... M22: =M9+M10+M14+M12 -> 0 | N22: =SUM(B22:M22) -> 22480 | O22: =IFERROR(AVERAGEIF(B22:M22,"<>0"),0) -> 7493.3333
A23: Taxa de poupança (plano sem seguro ÷ renda total) | B23: =N(Jan!C60) -> 0.185 | C23: =N(Fev!C60) -> 0.185 | D23: =N(Mar!C60) -> 0.185 | E23: =N(Abr!C60) -> 0 | F23: =N(Mai!C60) -> 0 | G23: =N(Jun!C60) -> 0 | H23: =N(Jul!C60) -> 0 | I23: =N(Ago!C60) -> 0 | J23: =N(Set!C60) -> 0 | K23: =N(Out!C60) -> 0 | L23: =N(Nov!C60) -> 0 | M23: =N(Dez!C60) -> 0 | N23: =IFERROR((N16-(N(Jan!C48)+N(Fev!C48)+N(Mar!C48)+N(Abr!C48)+N(Mai!C48)+N(Jun!C48)+N(Jul!C48)+N(Ago!C48)+N(Set!C48)+N(Out!C48)+N(Nov!C48)+N(Dez!C48)))/N8,0) -> 0.185
A25: Divisão das contas comuns do casal (proporcional à renda)
A26: ="Parte de "&Início!$C$6 -> Parte de Paula | B26: =IFERROR(O5/(O5+O6),0) -> 0.5625
A27: ="Parte de "&Início!$C$7 -> Parte de Marcos | B27: =IFERROR(O6/(O5+O6),0) -> 0.4375
A28: Cap. 29: cada um paga a mesma fatia do que ganha. Use o modo casal da calculadora de orçamento do blog.

Sheet Jan
A1: ="Orçamento de janeiro de "&Início!$C$5 -> Orçamento de janeiro de 2026
A2: Previsto: o que você planeja. Realizado: o que aconteceu, pelos extratos e faturas.
A3: Item | B3: Previsto | C3: Realizado | D3: Diferença | E3: Observação
A4: RENDA LÍQUIDA (depois de INSS e IR)
A5: ="Renda líquida de "&Início!$C$6 -> Renda líquida de Paula | B5: 4500 | C5: 4500 | D5: =IF(AND(B5="",C5=""),"",N(C5)-N(B5)) -> 0
A6: ="Renda líquida de "&Início!$C$7 -> Renda líquida de Marcos | B6: 3500 | C6: 3500 | D6: =IF(AND(B6="",C6=""),"",N(C6)-N(B6)) -> 0
A7: Outras rendas recorrentes (aluguel recebido, pensão) | D7: =IF(AND(B7="",C7=""),"",N(C7)-N(B7))
A8: Renda recorrente | B8: =SUM(B5:B7) -> 8000 | C8: =SUM(C5:C7) -> 8000 | D8: =N(C8)-N(B8) -> 0
A9: Entradas não recorrentes (13º, bônus, trabalhos avulsos) | D9: =IF(AND(B9="",C9=""),"",N(C9)-N(B9))
A10: Renda total | B10: =B8+N(B9) -> 8000 | C10: =C8+N(C9) -> 8000 | D10: =N(C10)-N(B10) -> 0
A12: ESSENCIAIS
A13: =Categorias!$C$6 -> Moradia (aluguel ou prestação, condomínio) | B13: 2000 | C13: 2000 | D13: =IF(AND(B13="",C13=""),"",N(C13)-N(B13)) -> 0
A14: =Categorias!$C$7 -> Contas da casa (luz, água, gás, internet, celular) | B14: 450 | C14: 450 | D14: =IF(AND(B14="",C14=""),"",N(C14)-N(B14)) -> 0
A15: =Categorias!$C$8 -> Alimentação (supermercado e feira) | B15: 1150 | C15: 1120 | D15: =IF(AND(B15="",C15=""),"",N(C15)-N(B15)) -> -30
A16: =Categorias!$C$9 -> Transporte (combustível, transporte público, aplicativo) | B16: 350 | C16: 350 | D16: =IF(AND(B16="",C16=""),"",N(C16)-N(B16)) -> 0
A17: =Categorias!$C$10 -> Saúde (plano, farmácia, consultas) | B17: 250 | C17: 250 | D17: =IF(AND(B17="",C17=""),"",N(C17)-N(B17)) -> 0
A18: =Categorias!$C$11 -> Outros essenciais | B18: 0 | D18: =IF(AND(B18="",C18=""),"",N(C18)-N(B18)) -> 0
A19: Total de essenciais | B19: =SUM(B13:B18) -> 4200 | C19: =SUM(C13:C18) -> 4170 | D19: =N(C19)-N(B19) -> -30
A21: COMPROMISSOS (parcelas e mensalidades com vencimento)
A22: =Categorias!$C$12 -> Financiamento ou empréstimo | B22: 0 | D22: =IF(AND(B22="",C22=""),"",N(C22)-N(B22)) -> 0
A23: =Categorias!$C$13 -> Parcela do carro | B23: 900 | C23: 900 | D23: =IF(AND(B23="",C23=""),"",N(C23)-N(B23)) -> 0
A24: =Categorias!$C$14 -> Escola, faculdade e cursos | B24: 400 | C24: 400 | D24: =IF(AND(B24="",C24=""),"",N(C24)-N(B24)) -> 0
A25: =Categorias!$C$15 -> Seguros mensais | B25: 0 | D25: =IF(AND(B25="",C25=""),"",N(C25)-N(B25)) -> 0
A26: =Categorias!$C$16 -> Outras parcelas e mensalidades | B26: 0 | D26: =IF(AND(B26="",C26=""),"",N(C26)-N(B26)) -> 0
A27: Total de compromissos | B27: =SUM(B22:B26) -> 1300 | C27: =SUM(C22:C26) -> 1300 | D27: =N(C27)-N(B27) -> 0
A29: DESPESAS IRREGULARES
A30: Provisão mensal (aba Irregulares, total ÷ 12) | B30: =Irregulares!$C$28 -> 500 | C30: =IF(N(C8)=0,"",Irregulares!$C$28) -> 500 | D30: =N(C30)-N(B30) -> 0
A31: Irregulares pagas neste mês (sai do dinheiro provisionado) | B31: =SUMIF(Irregulares!$D$6:$D$25,1,Irregulares!$C$6:$C$25) -> 1800 | C31: 1800 | D31: =IF(AND(B31="",C31=""),"",N(C31)-N(B31)) -> 0 | E31: Informativo: não entra na margem, que já desconta a provisão.
A33: MARGEM DE DECISÃO (renda recorrente - essenciais - compromissos - provisão) | B33: =B8-B19-B27-N(B30) -> 2000 | C33: =IF(N(C8)=0,"",C8-C19-C27-N(C30)) -> 2030 | D33: =N(C33)-N(B33) -> 30
A35: FLEXÍVEIS (saem da margem)
A36: =Categorias!$C$17 -> Restaurantes e delivery | B36: 150 | C36: 160 | D36: =IF(AND(B36="",C36=""),"",N(C36)-N(B36)) -> 10
A37: =Categorias!$C$18 -> Lazer e passeios | B37: 120 | C37: 120 | D37: =IF(AND(B37="",C37=""),"",N(C37)-N(B37)) -> 0
A38: =Categorias!$C$19 -> Compras (roupas, eletrônicos, casa) | B38: 80 | C38: 80 | D38: =IF(AND(B38="",C38=""),"",N(C38)-N(B38)) -> 0
A39: =Categorias!$C$20 -> Assinaturas e aplicativos | B39: 50 | C39: 50 | D39: =IF(AND(B39="",C39=""),"",N(C39)-N(B39)) -> 0
A40: =Categorias!$C$21 -> Cuidados pessoais | B40: 0 | D40: =IF(AND(B40="",C40=""),"",N(C40)-N(B40)) -> 0
A41: =Categorias!$C$22 -> Presentes e outros | B41: 0 | D41: =IF(AND(B41="",C41=""),"",N(C41)-N(B41)) -> 0
A42: Total de flexíveis | B42: =SUM(B36:B41) -> 400 | C42: =SUM(C36:C41) -> 410 | D42: =N(C42)-N(B42) -> 10
A43: MARGEM PARA O PLANO (margem de decisão - flexíveis) | B43: =N(B33)-B42 -> 1600 | C43: =IF(N(C8)=0,"",N(C33)-C42) -> 1620 | D43: =N(C43)-N(B43) -> 20
A45: DESTINO DA MARGEM (o seu plano, na ordem do cap. 35)
A46: Pagamento extra de dívidas caras | B46: 0 | D46: =IF(AND(B46="",C46=""),"",N(C46)-N(B46)) -> 0
A47: Reserva de emergência | B47: 1000 | C47: 1000 | D47: =IF(AND(B47="",C47=""),"",N(C47)-N(B47)) -> 0
A48: Seguro de vida e proteção | B48: 120 | C48: 120 | D48: =IF(AND(B48="",C48=""),"",N(C48)-N(B48)) -> 0
A49: =IF(Metas!$B$6="","Meta 1 (aba Metas)","Meta 1: "&Metas!$B$6) -> Meta 1: Entrada do apartamento | B49: 480 | C49: 480 | D49: =IF(AND(B49="",C49=""),"",N(C49)-N(B49)) -> 0
A50: =IF(Metas!$B$7="","Meta 2 (aba Metas)","Meta 2: "&Metas!$B$7) -> Meta 2: Faculdade do filho | B50: 0 | D50: =IF(AND(B50="",C50=""),"",N(C50)-N(B50)) -> 0
A51: =IF(Metas!$B$8="","Meta 3 (aba Metas)","Meta 3: "&Metas!$B$8) -> Meta 3 (aba Metas) | B51: 0 | D51: =IF(AND(B51="",C51=""),"",N(C51)-N(B51)) -> 0
A52: =IF(Metas!$B$9="","Meta 4 (aba Metas)","Meta 4: "&Metas!$B$9) -> Meta 4 (aba Metas) | B52: 0 | D52: =IF(AND(B52="",C52=""),"",N(C52)-N(B52)) -> 0
A53: =IF(Metas!$B$10="","Meta 5 (aba Metas)","Meta 5: "&Metas!$B$10) -> Meta 5 (aba Metas) | B53: 0 | D53: =IF(AND(B53="",C53=""),"",N(C53)-N(B53)) -> 0
A54: Aposentadoria (previdência ou investimentos de longo prazo) | B54: 0 | D54: =IF(AND(B54="",C54=""),"",N(C54)-N(B54)) -> 0
A55: Total do plano | B55: =SUM(B46:B54) -> 1600 | C55: =SUM(C46:C54) -> 1600 | D55: =N(C55)-N(B55) -> 0
A57: SALDO DO MÊS (margem para o plano - plano + entradas não recorrentes) | B57: =N(B43)-B55+N(B9) -> 0 | C57: =IF(N(C8)=0,"",N(C43)-C55+N(C9)) -> 20 | D57: =N(C57)-N(B57) -> 20 | E57: Negativo: o mês fechou no vermelho. Confira com o extrato.
A59: INDICADORES DO MÊS (realizado)
A60: Taxa de poupança (plano sem seguro ÷ renda total) | C60: =IFERROR((C55-N(C48))/C10,0) -> 0.185
A61: Necessidades (essenciais + compromissos + provisão) ÷ renda recorrente | C61: =IFERROR((C19+C27+N(C30))/C8,0) -> 0.74625
A62: Desejos (flexíveis) ÷ renda recorrente | C62: =IFERROR(C42/C8,0) -> 0.05125
A63: Plano (dívidas, reserva, metas, aposentadoria) ÷ renda recorrente | C63: =IFERROR(C55/C8,0) -> 0.2
A64: Referência 50/30/20: 50% necessidades, 30% desejos, 20% plano. É ponto de partida, não regra.

Sheet Fev
A1: ="Orçamento de fevereiro de "&Início!$C$5 -> Orçamento de fevereiro de 2026
A2: Previsto: o que você planeja. Realizado: o que aconteceu, pelos extratos e faturas. O previsto vem de janeiro; digite por cima se mudar.
A3: Item | B3: Previsto | C3: Realizado | D3: Diferença | E3: Observação
A4: RENDA LÍQUIDA (depois de INSS e IR)
A5: ="Renda líquida de "&Início!$C$6 -> Renda líquida de Paula | B5: =Jan!B5 -> 4500 | C5: 4500 | D5: =IF(AND(B5="",C5=""),"",N(C5)-N(B5)) -> 0
A6: ="Renda líquida de "&Início!$C$7 -> Renda líquida de Marcos | B6: =Jan!B6 -> 3500 | C6: 3500 | D6: =IF(AND(B6="",C6=""),"",N(C6)-N(B6)) -> 0
A7: Outras rendas recorrentes (aluguel recebido, pensão) | B7: =Jan!B7 -> 0 | D7: =IF(AND(B7="",C7=""),"",N(C7)-N(B7))
A8: Renda recorrente | B8: =SUM(B5:B7) -> 8000 | C8: =SUM(C5:C7) -> 8000 | D8: =N(C8)-N(B8) -> 0
A9: Entradas não recorrentes (13º, bônus, trabalhos avulsos) | B9: =Jan!B9 -> 0 | D9: =IF(AND(B9="",C9=""),"",N(C9)-N(B9))
A10: Renda total | B10: =B8+N(B9) -> 8000 | C10: =C8+N(C9) -> 8000 | D10: =N(C10)-N(B10) -> 0
A12: ESSENCIAIS
A13: =Categorias!$C$6 -> Moradia (aluguel ou prestação, condomínio) | B13: =Jan!B13 -> 2000 | C13: 2000 | D13: =IF(AND(B13="",C13=""),"",N(C13)-N(B13)) -> 0
A14: =Categorias!$C$7 -> Contas da casa (luz, água, gás, internet, celular) | B14: =Jan!B14 -> 450 | C14: 450 | D14: =IF(AND(B14="",C14=""),"",N(C14)-N(B14)) -> 0
A15: =Categorias!$C$8 -> Alimentação (supermercado e feira) | B15: =Jan!B15 -> 1150 | C15: 1120 | D15: =IF(AND(B15="",C15=""),"",N(C15)-N(B15)) -> -30
A16: =Categorias!$C$9 -> Transporte (combustível, transporte público, aplicativo) | B16: =Jan!B16 -> 350 | C16: 350 | D16: =IF(AND(B16="",C16=""),"",N(C16)-N(B16)) -> 0
A17: =Categorias!$C$10 -> Saúde (plano, farmácia, consultas) | B17: =Jan!B17 -> 250 | C17: 250 | D17: =IF(AND(B17="",C17=""),"",N(C17)-N(B17)) -> 0
A18: =Categorias!$C$11 -> Outros essenciais | B18: =Jan!B18 -> 0 | D18: =IF(AND(B18="",C18=""),"",N(C18)-N(B18)) -> 0
A19: Total de essenciais | B19: =SUM(B13:B18) -> 4200 | C19: =SUM(C13:C18) -> 4170 | D19: =N(C19)-N(B19) -> -30
A21: COMPROMISSOS (parcelas e mensalidades com vencimento)
A22: =Categorias!$C$12 -> Financiamento ou empréstimo | B22: =Jan!B22 -> 0 | D22: =IF(AND(B22="",C22=""),"",N(C22)-N(B22)) -> 0
A23: =Categorias!$C$13 -> Parcela do carro | B23: =Jan!B23 -> 900 | C23: 900 | D23: =IF(AND(B23="",C23=""),"",N(C23)-N(B23)) -> 0
A24: =Categorias!$C$14 -> Escola, faculdade e cursos | B24: =Jan!B24 -> 400 | C24: 400 | D24: =IF(AND(B24="",C24=""),"",N(C24)-N(B24)) -> 0
A25: =Categorias!$C$15 -> Seguros mensais | B25: =Jan!B25 -> 0 | D25: =IF(AND(B25="",C25=""),"",N(C25)-N(B25)) -> 0
A26: =Categorias!$C$16 -> Outras parcelas e mensalidades | B26: =Jan!B26 -> 0 | D26: =IF(AND(B26="",C26=""),"",N(C26)-N(B26)) -> 0
A27: Total de compromissos | B27: =SUM(B22:B26) -> 1300 | C27: =SUM(C22:C26) -> 1300 | D27: =N(C27)-N(B27) -> 0
A29: DESPESAS IRREGULARES
A30: Provisão mensal (aba Irregulares, total ÷ 12) | B30: =Irregulares!$C$28 -> 500 | C30: =IF(N(C8)=0,"",Irregulares!$C$28) -> 500 | D30: =N(C30)-N(B30) -> 0
A31: Irregulares pagas neste mês (sai do dinheiro provisionado) | B31: =SUMIF(Irregulares!$D$6:$D$25,2,Irregulares!$C$6:$C$25) -> 600 | C31: 600 | D31: =IF(AND(B31="",C31=""),"",N(C31)-N(B31)) -> 0 | E31: Informativo: não entra na margem, que já desconta a provisão.
A33: MARGEM DE DECISÃO (renda recorrente - essenciais - compromissos - provisão) | B33: =B8-B19-B27-N(B30) -> 2000 | C33: =IF(N(C8)=0,"",C8-C19-C27-N(C30)) -> 2030 | D33: =N(C33)-N(B33) -> 30
A35: FLEXÍVEIS (saem da margem)
A36: =Categorias!$C$17 -> Restaurantes e delivery | B36: =Jan!B36 -> 150 | C36: 150 | D36: =IF(AND(B36="",C36=""),"",N(C36)-N(B36)) -> 0
A37: =Categorias!$C$18 -> Lazer e passeios | B37: =Jan!B37 -> 120 | C37: 60 | D37: =IF(AND(B37="",C37=""),"",N(C37)-N(B37)) -> -60
A38: =Categorias!$C$19 -> Compras (roupas, eletrônicos, casa) | B38: =Jan!B38 -> 80 | C38: 80 | D38: =IF(AND(B38="",C38=""),"",N(C38)-N(B38)) -> 0
A39: =Categorias!$C$20 -> Assinaturas e aplicativos | B39: =Jan!B39 -> 50 | C39: 50 | D39: =IF(AND(B39="",C39=""),"",N(C39)-N(B39)) -> 0
A40: =Categorias!$C$21 -> Cuidados pessoais | B40: =Jan!B40 -> 0 | D40: =IF(AND(B40="",C40=""),"",N(C40)-N(B40)) -> 0
A41: =Categorias!$C$22 -> Presentes e outros | B41: =Jan!B41 -> 0 | D41: =IF(AND(B41="",C41=""),"",N(C41)-N(B41)) -> 0
A42: Total de flexíveis | B42: =SUM(B36:B41) -> 400 | C42: =SUM(C36:C41) -> 340 | D42: =N(C42)-N(B42) -> -60
A43: MARGEM PARA O PLANO (margem de decisão - flexíveis) | B43: =N(B33)-B42 -> 1600 | C43: =IF(N(C8)=0,"",N(C33)-C42) -> 1690 | D43: =N(C43)-N(B43) -> 90
A45: DESTINO DA MARGEM (o seu plano, na ordem do cap. 35)
A46: Pagamento extra de dívidas caras | B46: =Jan!B46 -> 0 | D46: =IF(AND(B46="",C46=""),"",N(C46)-N(B46)) -> 0
A47: Reserva de emergência | B47: =Jan!B47 -> 1000 | C47: 1000 | D47: =IF(AND(B47="",C47=""),"",N(C47)-N(B47)) -> 0
A48: Seguro de vida e proteção | B48: =Jan!B48 -> 120 | C48: 120 | D48: =IF(AND(B48="",C48=""),"",N(C48)-N(B48)) -> 0
A49: =IF(Metas!$B$6="","Meta 1 (aba Metas)","Meta 1: "&Metas!$B$6) -> Meta 1: Entrada do apartamento | B49: =Jan!B49 -> 480 | C49: 480 | D49: =IF(AND(B49="",C49=""),"",N(C49)-N(B49)) -> 0
A50: =IF(Metas!$B$7="","Meta 2 (aba Metas)","Meta 2: "&Metas!$B$7) -> Meta 2: Faculdade do filho | B50: =Jan!B50 -> 0 | D50: =IF(AND(B50="",C50=""),"",N(C50)-N(B50)) -> 0
A51: =IF(Metas!$B$8="","Meta 3 (aba Metas)","Meta 3: "&Metas!$B$8) -> Meta 3 (aba Metas) | B51: =Jan!B51 -> 0 | D51: =IF(AND(B51="",C51=""),"",N(C51)-N(B51)) -> 0
A52: =IF(Metas!$B$9="","Meta 4 (aba Metas)","Meta 4: "&Metas!$B$9) -> Meta 4 (aba Metas) | B52: =Jan!B52 -> 0 | D52: =IF(AND(B52="",C52=""),"",N(C52)-N(B52)) -> 0
A53: =IF(Metas!$B$10="","Meta 5 (aba Metas)","Meta 5: "&Metas!$B$10) -> Meta 5 (aba Metas) | B53: =Jan!B53 -> 0 | D53: =IF(AND(B53="",C53=""),"",N(C53)-N(B53)) -> 0
A54: Aposentadoria (previdência ou investimentos de longo prazo) | B54: =Jan!B54 -> 0 | D54: =IF(AND(B54="",C54=""),"",N(C54)-N(B54)) -> 0
A55: Total do plano | B55: =SUM(B46:B54) -> 1600 | C55: =SUM(C46:C54) -> 1600 | D55: =N(C55)-N(B55) -> 0
A57: SALDO DO MÊS (margem para o plano - plano + entradas não recorrentes) | B57: =N(B43)-B55+N(B9) -> 0 | C57: =IF(N(C8)=0,"",N(C43)-C55+N(C9)) -> 90 | D57: =N(C57)-N(B57) -> 90 | E57: Negativo: o mês fechou no vermelho. Confira com o extrato.
A59: INDICADORES DO MÊS (realizado)
A60: Taxa de poupança (plano sem seguro ÷ renda total) | C60: =IFERROR((C55-N(C48))/C10,0) -> 0.185
A61: Necessidades (essenciais + compromissos + provisão) ÷ renda recorrente | C61: =IFERROR((C19+C27+N(C30))/C8,0) -> 0.74625
A62: Desejos (flexíveis) ÷ renda recorrente | C62: =IFERROR(C42/C8,0) -> 0.0425
A63: Plano (dívidas, reserva, metas, aposentadoria) ÷ renda recorrente | C63: =IFERROR(C55/C8,0) -> 0.2
A64: Referência 50/30/20: 50% necessidades, 30% desejos, 20% plano. É ponto de partida, não regra.

Sheet Mar
A1: ="Orçamento de março de "&Início!$C$5 -> Orçamento de março de 2026
A2: Previsto: o que você planeja. Realizado: o que aconteceu, pelos extratos e faturas. O previsto vem de fevereiro; digite por cima se mudar.
A3: Item | B3: Previsto | C3: Realizado | D3: Diferença | E3: Observação
A4: RENDA LÍQUIDA (depois de INSS e IR)
A5: ="Renda líquida de "&Início!$C$6 -> Renda líquida de Paula | B5: =Fev!B5 -> 4500 | C5: 4500 | D5: =IF(AND(B5="",C5=""),"",N(C5)-N(B5)) -> 0
A6: ="Renda líquida de "&Início!$C$7 -> Renda líquida de Marcos | B6: =Fev!B6 -> 3500 | C6: 3500 | D6: =IF(AND(B6="",C6=""),"",N(C6)-N(B6)) -> 0
A7: Outras rendas recorrentes (aluguel recebido, pensão) | B7: =Fev!B7 -> 0 | D7: =IF(AND(B7="",C7=""),"",N(C7)-N(B7))
A8: Renda recorrente | B8: =SUM(B5:B7) -> 8000 | C8: =SUM(C5:C7) -> 8000 | D8: =N(C8)-N(B8) -> 0
A9: Entradas não recorrentes (13º, bônus, trabalhos avulsos) | B9: =Fev!B9 -> 0 | C9: 0 | D9: =IF(AND(B9="",C9=""),"",N(C9)-N(B9)) -> 0
A10: Renda total | B10: =B8+N(B9) -> 8000 | C10: =C8+N(C9) -> 8000 | D10: =N(C10)-N(B10) -> 0
A12: ESSENCIAIS
A13: =Categorias!$C$6 -> Moradia (aluguel ou prestação, condomínio) | B13: =Fev!B13 -> 2000 | C13: 2000 | D13: =IF(AND(B13="",C13=""),"",N(C13)-N(B13)) -> 0
A14: =Categorias!$C$7 -> Contas da casa (luz, água, gás, internet, celular) | B14: =Fev!B14 -> 450 | C14: 430 | D14: =IF(AND(B14="",C14=""),"",N(C14)-N(B14)) -> -20
A15: =Categorias!$C$8 -> Alimentação (supermercado e feira) | B15: =Fev!B15 -> 1150 | C15: 1150 | D15: =IF(AND(B15="",C15=""),"",N(C15)-N(B15)) -> 0
A16: =Categorias!$C$9 -> Transporte (combustível, transporte público, aplicativo) | B16: =Fev!B16 -> 350 | C16: 390 | D16: =IF(AND(B16="",C16=""),"",N(C16)-N(B16)) -> 40
A17: =Categorias!$C$10 -> Saúde (plano, farmácia, consultas) | B17: =Fev!B17 -> 250 | C17: 250 | D17: =IF(AND(B17="",C17=""),"",N(C17)-N(B17)) -> 0
A18: =Categorias!$C$11 -> Outros essenciais | B18: =Fev!B18 -> 0 | D18: =IF(AND(B18="",C18=""),"",N(C18)-N(B18)) -> 0
A19: Total de essenciais | B19: =SUM(B13:B18) -> 4200 | C19: =SUM(C13:C18) -> 4220 | D19: =N(C19)-N(B19) -> 20
A21: COMPROMISSOS (parcelas e mensalidades com vencimento)
A22: =Categorias!$C$12 -> Financiamento ou empréstimo | B22: =Fev!B22 -> 0 | D22: =IF(AND(B22="",C22=""),"",N(C22)-N(B22)) -> 0
A23: =Categorias!$C$13 -> Parcela do carro | B23: =Fev!B23 -> 900 | C23: 900 | D23: =IF(AND(B23="",C23=""),"",N(C23)-N(B23)) -> 0
A24: =Categorias!$C$14 -> Escola, faculdade e cursos | B24: =Fev!B24 -> 400 | C24: 400 | D24: =IF(AND(B24="",C24=""),"",N(C24)-N(B24)) -> 0
A25: =Categorias!$C$15 -> Seguros mensais | B25: =Fev!B25 -> 0 | D25: =IF(AND(B25="",C25=""),"",N(C25)-N(B25)) -> 0
A26: =Categorias!$C$16 -> Outras parcelas e mensalidades | B26: =Fev!B26 -> 0 | D26: =IF(AND(B26="",C26=""),"",N(C26)-N(B26)) -> 0
A27: Total de compromissos | B27: =SUM(B22:B26) -> 1300 | C27: =SUM(C22:C26) -> 1300 | D27: =N(C27)-N(B27) -> 0
A29: DESPESAS IRREGULARES
A30: Provisão mensal (aba Irregulares, total ÷ 12) | B30: =Irregulares!$C$28 -> 500 | C30: =IF(N(C8)=0,"",Irregulares!$C$28) -> 500 | D30: =N(C30)-N(B30) -> 0
A31: Irregulares pagas neste mês (sai do dinheiro provisionado) | B31: =SUMIF(Irregulares!$D$6:$D$25,3,Irregulares!$C$6:$C$25) -> 2400 | C31: 2400 | D31: =IF(AND(B31="",C31=""),"",N(C31)-N(B31)) -> 0 | E31: Informativo: não entra na margem, que já desconta a provisão.
A33: MARGEM DE DECISÃO (renda recorrente - essenciais - compromissos - provisão) | B33: =B8-B19-B27-N(B30) -> 2000 | C33: =IF(N(C8)=0,"",C8-C19-C27-N(C30)) -> 1980 | D33: =N(C33)-N(B33) -> -20
A35: FLEXÍVEIS (saem da margem)
A36: =Categorias!$C$17 -> Restaurantes e delivery | B36: =Fev!B36 -> 150 | C36: 150 | D36: =IF(AND(B36="",C36=""),"",N(C36)-N(B36)) -> 0
A37: =Categorias!$C$18 -> Lazer e passeios | B37: =Fev!B37 -> 120 | C37: 120 | D37: =IF(AND(B37="",C37=""),"",N(C37)-N(B37)) -> 0
A38: =Categorias!$C$19 -> Compras (roupas, eletrônicos, casa) | B38: =Fev!B38 -> 80 | C38: 150 | D38: =IF(AND(B38="",C38=""),"",N(C38)-N(B38)) -> 70
A39: =Categorias!$C$20 -> Assinaturas e aplicativos | B39: =Fev!B39 -> 50 | C39: 50 | D39: =IF(AND(B39="",C39=""),"",N(C39)-N(B39)) -> 0
A40: =Categorias!$C$21 -> Cuidados pessoais | B40: =Fev!B40 -> 0 | D40: =IF(AND(B40="",C40=""),"",N(C40)-N(B40)) -> 0
A41: =Categorias!$C$22 -> Presentes e outros | B41: =Fev!B41 -> 0 | D41: =IF(AND(B41="",C41=""),"",N(C41)-N(B41)) -> 0
A42: Total de flexíveis | B42: =SUM(B36:B41) -> 400 | C42: =SUM(C36:C41) -> 470 | D42: =N(C42)-N(B42) -> 70
A43: MARGEM PARA O PLANO (margem de decisão - flexíveis) | B43: =N(B33)-B42 -> 1600 | C43: =IF(N(C8)=0,"",N(C33)-C42) -> 1510 | D43: =N(C43)-N(B43) -> -90
A45: DESTINO DA MARGEM (o seu plano, na ordem do cap. 35)
A46: Pagamento extra de dívidas caras | B46: =Fev!B46 -> 0 | D46: =IF(AND(B46="",C46=""),"",N(C46)-N(B46)) -> 0
A47: Reserva de emergência | B47: =Fev!B47 -> 1000 | C47: 1000 | D47: =IF(AND(B47="",C47=""),"",N(C47)-N(B47)) -> 0
A48: Seguro de vida e proteção | B48: =Fev!B48 -> 120 | C48: 120 | D48: =IF(AND(B48="",C48=""),"",N(C48)-N(B48)) -> 0
A49: =IF(Metas!$B$6="","Meta 1 (aba Metas)","Meta 1: "&Metas!$B$6) -> Meta 1: Entrada do apartamento | B49: =Fev!B49 -> 480 | C49: 480 | D49: =IF(AND(B49="",C49=""),"",N(C49)-N(B49)) -> 0
A50: =IF(Metas!$B$7="","Meta 2 (aba Metas)","Meta 2: "&Metas!$B$7) -> Meta 2: Faculdade do filho | B50: =Fev!B50 -> 0 | D50: =IF(AND(B50="",C50=""),"",N(C50)-N(B50)) -> 0
A51: =IF(Metas!$B$8="","Meta 3 (aba Metas)","Meta 3: "&Metas!$B$8) -> Meta 3 (aba Metas) | B51: =Fev!B51 -> 0 | D51: =IF(AND(B51="",C51=""),"",N(C51)-N(B51)) -> 0
A52: =IF(Metas!$B$9="","Meta 4 (aba Metas)","Meta 4: "&Metas!$B$9) -> Meta 4 (aba Metas) | B52: =Fev!B52 -> 0 | D52: =IF(AND(B52="",C52=""),"",N(C52)-N(B52)) -> 0
A53: =IF(Metas!$B$10="","Meta 5 (aba Metas)","Meta 5: "&Metas!$B$10) -> Meta 5 (aba Metas) | B53: =Fev!B53 -> 0 | D53: =IF(AND(B53="",C53=""),"",N(C53)-N(B53)) -> 0
A54: Aposentadoria (previdência ou investimentos de longo prazo) | B54: =Fev!B54 -> 0 | D54: =IF(AND(B54="",C54=""),"",N(C54)-N(B54)) -> 0
A55: Total do plano | B55: =SUM(B46:B54) -> 1600 | C55: =SUM(C46:C54) -> 1600 | D55: =N(C55)-N(B55) -> 0
A57: SALDO DO MÊS (margem para o plano - plano + entradas não recorrentes) | B57: =N(B43)-B55+N(B9) -> 0 | C57: =IF(N(C8)=0,"",N(C43)-C55+N(C9)) -> -90 | D57: =N(C57)-N(B57) -> -90 | E57: Negativo: o mês fechou no vermelho. Confira com o extrato.
A59: INDICADORES DO MÊS (realizado)
A60: Taxa de poupança (plano sem seguro ÷ renda total) | C60: =IFERROR((C55-N(C48))/C10,0) -> 0.185
A61: Necessidades (essenciais + compromissos + provisão) ÷ renda recorrente | C61: =IFERROR((C19+C27+N(C30))/C8,0) -> 0.7525
A62: Desejos (flexíveis) ÷ renda recorrente | C62: =IFERROR(C42/C8,0) -> 0.05875
A63: Plano (dívidas, reserva, metas, aposentadoria) ÷ renda recorrente | C63: =IFERROR(C55/C8,0) -> 0.2
A64: Referência 50/30/20: 50% necessidades, 30% desejos, 20% plano. É ponto de partida, não regra.

Sheet Abr
A1: ="Orçamento de abril de "&Início!$C$5 -> Orçamento de abril de 2026
A2: Previsto: o que você planeja. Realizado: o que aconteceu, pelos extratos e faturas. O previsto vem de março; digite por cima se mudar.
A3: Item | B3: Previsto | C3: Realizado | D3: Diferença | E3: Observação
A4: RENDA LÍQUIDA (depois de INSS e IR)
A5: ="Renda líquida de "&Início!$C$6 -> Renda líquida de Paula | B5: =Mar!B5 -> 4500 | D5: =IF(AND(B5="",C5=""),"",N(C5)-N(B5)) -> -4500
A6: ="Renda líquida de "&Início!$C$7 -> Renda líquida de Marcos | B6: =Mar!B6 -> 3500 | D6: =IF(AND(B6="",C6=""),"",N(C6)-N(B6)) -> -3500
A7: Outras rendas recorrentes (aluguel recebido, pensão) | B7: =Mar!B7 -> 0 | D7: =IF(AND(B7="",C7=""),"",N(C7)-N(B7))
A8: Renda recorrente | B8: =SUM(B5:B7) -> 8000 | C8: =SUM(C5:C7) -> 0 | D8: =N(C8)-N(B8) -> -8000
A9: Entradas não recorrentes (13º, bônus, trabalhos avulsos) | B9: =Mar!B9 -> 0 | D9: =IF(AND(B9="",C9=""),"",N(C9)-N(B9))
A10: Renda total | B10: =B8+N(B9) -> 8000 | C10: =C8+N(C9) -> 0 | D10: =N(C10)-N(B10) -> -8000
A12: ESSENCIAIS
A13: =Categorias!$C$6 -> Moradia (aluguel ou prestação, condomínio) | B13: =Mar!B13 -> 2000 | D13: =IF(AND(B13="",C13=""),"",N(C13)-N(B13)) -> -2000
A14: =Categorias!$C$7 -> Contas da casa (luz, água, gás, internet, celular) | B14: =Mar!B14 -> 450 | D14: =IF(AND(B14="",C14=""),"",N(C14)-N(B14)) -> -450
A15: =Categorias!$C$8 -> Alimentação (supermercado e feira) | B15: =Mar!B15 -> 1150 | D15: =IF(AND(B15="",C15=""),"",N(C15)-N(B15)) -> -1150
A16: =Categorias!$C$9 -> Transporte (combustível, transporte público, aplicativo) | B16: =Mar!B16 -> 350 | D16: =IF(AND(B16="",C16=""),"",N(C16)-N(B16)) -> -350
A17: =Categorias!$C$10 -> Saúde (plano, farmácia, consultas) | B17: =Mar!B17 -> 250 | D17: =IF(AND(B17="",C17=""),"",N(C17)-N(B17)) -> -250
A18: =Categorias!$C$11 -> Outros essenciais | B18: =Mar!B18 -> 0 | D18: =IF(AND(B18="",C18=""),"",N(C18)-N(B18)) -> 0
A19: Total de essenciais | B19: =SUM(B13:B18) -> 4200 | C19: =SUM(C13:C18) -> 0 | D19: =N(C19)-N(B19) -> -4200
A21: COMPROMISSOS (parcelas e mensalidades com vencimento)
A22: =Categorias!$C$12 -> Financiamento ou empréstimo | B22: =Mar!B22 -> 0 | D22: =IF(AND(B22="",C22=""),"",N(C22)-N(B22)) -> 0
A23: =Categorias!$C$13 -> Parcela do carro | B23: =Mar!B23 -> 900 | D23: =IF(AND(B23="",C23=""),"",N(C23)-N(B23)) -> -900
A24: =Categorias!$C$14 -> Escola, faculdade e cursos | B24: =Mar!B24 -> 400 | D24: =IF(AND(B24="",C24=""),"",N(C24)-N(B24)) -> -400
A25: =Categorias!$C$15 -> Seguros mensais | B25: =Mar!B25 -> 0 | D25: =IF(AND(B25="",C25=""),"",N(C25)-N(B25)) -> 0
A26: =Categorias!$C$16 -> Outras parcelas e mensalidades | B26: =Mar!B26 -> 0 | D26: =IF(AND(B26="",C26=""),"",N(C26)-N(B26)) -> 0
A27: Total de compromissos | B27: =SUM(B22:B26) -> 1300 | C27: =SUM(C22:C26) -> 0 | D27: =N(C27)-N(B27) -> -1300
A29: DESPESAS IRREGULARES
A30: Provisão mensal (aba Irregulares, total ÷ 12) | B30: =Irregulares!$C$28 -> 500 | C30: =IF(N(C8)=0,"",Irregulares!$C$28) | D30: =N(C30)-N(B30) -> -500
A31: Irregulares pagas neste mês (sai do dinheiro provisionado) | B31: =SUMIF(Irregulares!$D$6:$D$25,4,Irregulares!$C$6:$C$25) -> 0 | D31: =IF(AND(B31="",C31=""),"",N(C31)-N(B31)) -> 0 | E31: Informativo: não entra na margem, que já desconta a provisão.
A33: MARGEM DE DECISÃO (renda recorrente - essenciais - compromissos - provisão) | B33: =B8-B19-B27-N(B30) -> 2000 | C33: =IF(N(C8)=0,"",C8-C19-C27-N(C30)) | D33: =N(C33)-N(B33) -> -2000
A35: FLEXÍVEIS (saem da margem)
A36: =Categorias!$C$17 -> Restaurantes e delivery | B36: =Mar!B36 -> 150 | D36: =IF(AND(B36="",C36=""),"",N(C36)-N(B36)) -> -150
A37: =Categorias!$C$18 -> Lazer e passeios | B37: =Mar!B37 -> 120 | D37: =IF(AND(B37="",C37=""),"",N(C37)-N(B37)) -> -120
A38: =Categorias!$C$19 -> Compras (roupas, eletrônicos, casa) | B38: =Mar!B38 -> 80 | D38: =IF(AND(B38="",C38=""),"",N(C38)-N(B38)) -> -80
A39: =Categorias!$C$20 -> Assinaturas e aplicativos | B39: =Mar!B39 -> 50 | D39: =IF(AND(B39="",C39=""),"",N(C39)-N(B39)) -> -50
A40: =Categorias!$C$21 -> Cuidados pessoais | B40: =Mar!B40 -> 0 | D40: =IF(AND(B40="",C40=""),"",N(C40)-N(B40)) -> 0
A41: =Categorias!$C$22 -> Presentes e outros | B41: =Mar!B41 -> 0 | D41: =IF(AND(B41="",C41=""),"",N(C41)-N(B41)) -> 0
A42: Total de flexíveis | B42: =SUM(B36:B41) -> 400 | C42: =SUM(C36:C41) -> 0 | D42: =N(C42)-N(B42) -> -400
A43: MARGEM PARA O PLANO (margem de decisão - flexíveis) | B43: =N(B33)-B42 -> 1600 | C43: =IF(N(C8)=0,"",N(C33)-C42) | D43: =N(C43)-N(B43) -> -1600
A45: DESTINO DA MARGEM (o seu plano, na ordem do cap. 35)
A46: Pagamento extra de dívidas caras | B46: =Mar!B46 -> 0 | D46: =IF(AND(B46="",C46=""),"",N(C46)-N(B46)) -> 0
A47: Reserva de emergência | B47: =Mar!B47 -> 1000 | D47: =IF(AND(B47="",C47=""),"",N(C47)-N(B47)) -> -1000
A48: Seguro de vida e proteção | B48: =Mar!B48 -> 120 | D48: =IF(AND(B48="",C48=""),"",N(C48)-N(B48)) -> -120
A49: =IF(Metas!$B$6="","Meta 1 (aba Metas)","Meta 1: "&Metas!$B$6) -> Meta 1: Entrada do apartamento | B49: =Mar!B49 -> 480 | D49: =IF(AND(B49="",C49=""),"",N(C49)-N(B49)) -> -480
A50: =IF(Metas!$B$7="","Meta 2 (aba Metas)","Meta 2: "&Metas!$B$7) -> Meta 2: Faculdade do filho | B50: =Mar!B50 -> 0 | D50: =IF(AND(B50="",C50=""),"",N(C50)-N(B50)) -> 0
A51: =IF(Metas!$B$8="","Meta 3 (aba Metas)","Meta 3: "&Metas!$B$8) -> Meta 3 (aba Metas) | B51: =Mar!B51 -> 0 | D51: =IF(AND(B51="",C51=""),"",N(C51)-N(B51)) -> 0
A52: =IF(Metas!$B$9="","Meta 4 (aba Metas)","Meta 4: "&Metas!$B$9) -> Meta 4 (aba Metas) | B52: =Mar!B52 -> 0 | D52: =IF(AND(B52="",C52=""),"",N(C52)-N(B52)) -> 0
A53: =IF(Metas!$B$10="","Meta 5 (aba Metas)","Meta 5: "&Metas!$B$10) -> Meta 5 (aba Metas) | B53: =Mar!B53 -> 0 | D53: =IF(AND(B53="",C53=""),"",N(C53)-N(B53)) -> 0
A54: Aposentadoria (previdência ou investimentos de longo prazo) | B54: =Mar!B54 -> 0 | D54: =IF(AND(B54="",C54=""),"",N(C54)-N(B54)) -> 0
A55: Total do plano | B55: =SUM(B46:B54) -> 1600 | C55: =SUM(C46:C54) -> 0 | D55: =N(C55)-N(B55) -> -1600
A57: SALDO DO MÊS (margem para o plano - plano + entradas não recorrentes) | B57: =N(B43)-B55+N(B9) -> 0 | C57: =IF(N(C8)=0,"",N(C43)-C55+N(C9)) | D57: =N(C57)-N(B57) -> 0 | E57: Negativo: o mês fechou no vermelho. Confira com o extrato.
A59: INDICADORES DO MÊS (realizado)
A60: Taxa de poupança (plano sem seguro ÷ renda total) | C60: =IFERROR((C55-N(C48))/C10,0) -> 0
A61: Necessidades (essenciais + compromissos + provisão) ÷ renda recorrente | C61: =IFERROR((C19+C27+N(C30))/C8,0) -> 0
A62: Desejos (flexíveis) ÷ renda recorrente | C62: =IFERROR(C42/C8,0) -> 0
A63: Plano (dívidas, reserva, metas, aposentadoria) ÷ renda recorrente | C63: =IFERROR(C55/C8,0) -> 0
A64: Referência 50/30/20: 50% necessidades, 30% desejos, 20% plano. É ponto de partida, não regra.

Sheet Mai
A1: ="Orçamento de maio de "&Início!$C$5 -> Orçamento de maio de 2026
A2: Previsto: o que você planeja. Realizado: o que aconteceu, pelos extratos e faturas. O previsto vem de abril; digite por cima se mudar.
A3: Item | B3: Previsto | C3: Realizado | D3: Diferença | E3: Observação
A4: RENDA LÍQUIDA (depois de INSS e IR)
A5: ="Renda líquida de "&Início!$C$6 -> Renda líquida de Paula | B5: =Abr!B5 -> 4500 | D5: =IF(AND(B5="",C5=""),"",N(C5)-N(B5)) -> -4500
A6: ="Renda líquida de "&Início!$C$7 -> Renda líquida de Marcos | B6: =Abr!B6 -> 3500 | D6: =IF(AND(B6="",C6=""),"",N(C6)-N(B6)) -> -3500
A7: Outras rendas recorrentes (aluguel recebido, pensão) | B7: =Abr!B7 -> 0 | D7: =IF(AND(B7="",C7=""),"",N(C7)-N(B7))
A8: Renda recorrente | B8: =SUM(B5:B7) -> 8000 | C8: =SUM(C5:C7) -> 0 | D8: =N(C8)-N(B8) -> -8000
A9: Entradas não recorrentes (13º, bônus, trabalhos avulsos) | B9: =Abr!B9 -> 0 | D9: =IF(AND(B9="",C9=""),"",N(C9)-N(B9))
A10: Renda total | B10: =B8+N(B9) -> 8000 | C10: =C8+N(C9) -> 0 | D10: =N(C10)-N(B10) -> -8000
A12: ESSENCIAIS
A13: =Categorias!$C$6 -> Moradia (aluguel ou prestação, condomínio) | B13: =Abr!B13 -> 2000 | D13: =IF(AND(B13="",C13=""),"",N(C13)-N(B13)) -> -2000
A14: =Categorias!$C$7 -> Contas da casa (luz, água, gás, internet, celular) | B14: =Abr!B14 -> 450 | D14: =IF(AND(B14="",C14=""),"",N(C14)-N(B14)) -> -450
A15: =Categorias!$C$8 -> Alimentação (supermercado e feira) | B15: =Abr!B15 -> 1150 | D15: =IF(AND(B15="",C15=""),"",N(C15)-N(B15)) -> -1150
A16: =Categorias!$C$9 -> Transporte (combustível, transporte público, aplicativo) | B16: =Abr!B16 -> 350 | D16: =IF(AND(B16="",C16=""),"",N(C16)-N(B16)) -> -350
A17: =Categorias!$C$10 -> Saúde (plano, farmácia, consultas) | B17: =Abr!B17 -> 250 | D17: =IF(AND(B17="",C17=""),"",N(C17)-N(B17)) -> -250
A18: =Categorias!$C$11 -> Outros essenciais | B18: =Abr!B18 -> 0 | D18: =IF(AND(B18="",C18=""),"",N(C18)-N(B18)) -> 0
A19: Total de essenciais | B19: =SUM(B13:B18) -> 4200 | C19: =SUM(C13:C18) -> 0 | D19: =N(C19)-N(B19) -> -4200
A21: COMPROMISSOS (parcelas e mensalidades com vencimento)
A22: =Categorias!$C$12 -> Financiamento ou empréstimo | B22: =Abr!B22 -> 0 | D22: =IF(AND(B22="",C22=""),"",N(C22)-N(B22)) -> 0
A23: =Categorias!$C$13 -> Parcela do carro | B23: =Abr!B23 -> 900 | D23: =IF(AND(B23="",C23=""),"",N(C23)-N(B23)) -> -900
A24: =Categorias!$C$14 -> Escola, faculdade e cursos | B24: =Abr!B24 -> 400 | D24: =IF(AND(B24="",C24=""),"",N(C24)-N(B24)) -> -400
A25: =Categorias!$C$15 -> Seguros mensais | B25: =Abr!B25 -> 0 | D25: =IF(AND(B25="",C25=""),"",N(C25)-N(B25)) -> 0
A26: =Categorias!$C$16 -> Outras parcelas e mensalidades | B26: =Abr!B26 -> 0 | D26: =IF(AND(B26="",C26=""),"",N(C26)-N(B26)) -> 0
A27: Total de compromissos | B27: =SUM(B22:B26) -> 1300 | C27: =SUM(C22:C26) -> 0 | D27: =N(C27)-N(B27) -> -1300
A29: DESPESAS IRREGULARES
A30: Provisão mensal (aba Irregulares, total ÷ 12) | B30: =Irregulares!$C$28 -> 500 | C30: =IF(N(C8)=0,"",Irregulares!$C$28) | D30: =N(C30)-N(B30) -> -500
A31: Irregulares pagas neste mês (sai do dinheiro provisionado) | B31: =SUMIF(Irregulares!$D$6:$D$25,5,Irregulares!$C$6:$C$25) -> 0 | D31: =IF(AND(B31="",C31=""),"",N(C31)-N(B31)) -> 0 | E31: Informativo: não entra na margem, que já desconta a provisão.
A33: MARGEM DE DECISÃO (renda recorrente - essenciais - compromissos - provisão) | B33: =B8-B19-B27-N(B30) -> 2000 | C33: =IF(N(C8)=0,"",C8-C19-C27-N(C30)) | D33: =N(C33)-N(B33) -> -2000
A35: FLEXÍVEIS (saem da margem)
A36: =Categorias!$C$17 -> Restaurantes e delivery | B36: =Abr!B36 -> 150 | D36: =IF(AND(B36="",C36=""),"",N(C36)-N(B36)) -> -150
A37: =Categorias!$C$18 -> Lazer e passeios | B37: =Abr!B37 -> 120 | D37: =IF(AND(B37="",C37=""),"",N(C37)-N(B37)) -> -120
A38: =Categorias!$C$19 -> Compras (roupas, eletrônicos, casa) | B38: =Abr!B38 -> 80 | D38: =IF(AND(B38="",C38=""),"",N(C38)-N(B38)) -> -80
A39: =Categorias!$C$20 -> Assinaturas e aplicativos | B39: =Abr!B39 -> 50 | D39: =IF(AND(B39="",C39=""),"",N(C39)-N(B39)) -> -50
A40: =Categorias!$C$21 -> Cuidados pessoais | B40: =Abr!B40 -> 0 | D40: =IF(AND(B40="",C40=""),"",N(C40)-N(B40)) -> 0
A41: =Categorias!$C$22 -> Presentes e outros | B41: =Abr!B41 -> 0 | D41: =IF(AND(B41="",C41=""),"",N(C41)-N(B41)) -> 0
A42: Total de flexíveis | B42: =SUM(B36:B41) -> 400 | C42: =SUM(C36:C41) -> 0 | D42: =N(C42)-N(B42) -> -400
A43: MARGEM PARA O PLANO (margem de decisão - flexíveis) | B43: =N(B33)-B42 -> 1600 | C43: =IF(N(C8)=0,"",N(C33)-C42) | D43: =N(C43)-N(B43) -> -1600
A45: DESTINO DA MARGEM (o seu plano, na ordem do cap. 35)
A46: Pagamento extra de dívidas caras | B46: =Abr!B46 -> 0 | D46: =IF(AND(B46="",C46=""),"",N(C46)-N(B46)) -> 0
A47: Reserva de emergência | B47: =Abr!B47 -> 1000 | D47: =IF(AND(B47="",C47=""),"",N(C47)-N(B47)) -> -1000
A48: Seguro de vida e proteção | B48: =Abr!B48 -> 120 | D48: =IF(AND(B48="",C48=""),"",N(C48)-N(B48)) -> -120
A49: =IF(Metas!$B$6="","Meta 1 (aba Metas)","Meta 1: "&Metas!$B$6) -> Meta 1: Entrada do apartamento | B49: =Abr!B49 -> 480 | D49: =IF(AND(B49="",C49=""),"",N(C49)-N(B49)) -> -480
A50: =IF(Metas!$B$7="","Meta 2 (aba Metas)","Meta 2: "&Metas!$B$7) -> Meta 2: Faculdade do filho | B50: =Abr!B50 -> 0 | D50: =IF(AND(B50="",C50=""),"",N(C50)-N(B50)) -> 0
A51: =IF(Metas!$B$8="","Meta 3 (aba Metas)","Meta 3: "&Metas!$B$8) -> Meta 3 (aba Metas) | B51: =Abr!B51 -> 0 | D51: =IF(AND(B51="",C51=""),"",N(C51)-N(B51)) -> 0
A52: =IF(Metas!$B$9="","Meta 4 (aba Metas)","Meta 4: "&Metas!$B$9) -> Meta 4 (aba Metas) | B52: =Abr!B52 -> 0 | D52: =IF(AND(B52="",C52=""),"",N(C52)-N(B52)) -> 0
A53: =IF(Metas!$B$10="","Meta 5 (aba Metas)","Meta 5: "&Metas!$B$10) -> Meta 5 (aba Metas) | B53: =Abr!B53 -> 0 | D53: =IF(AND(B53="",C53=""),"",N(C53)-N(B53)) -> 0
A54: Aposentadoria (previdência ou investimentos de longo prazo) | B54: =Abr!B54 -> 0 | D54: =IF(AND(B54="",C54=""),"",N(C54)-N(B54)) -> 0
A55: Total do plano | B55: =SUM(B46:B54) -> 1600 | C55: =SUM(C46:C54) -> 0 | D55: =N(C55)-N(B55) -> -1600
A57: SALDO DO MÊS (margem para o plano - plano + entradas não recorrentes) | B57: =N(B43)-B55+N(B9) -> 0 | C57: =IF(N(C8)=0,"",N(C43)-C55+N(C9)) | D57: =N(C57)-N(B57) -> 0 | E57: Negativo: o mês fechou no vermelho. Confira com o extrato.
A59: INDICADORES DO MÊS (realizado)
A60: Taxa de poupança (plano sem seguro ÷ renda total) | C60: =IFERROR((C55-N(C48))/C10,0) -> 0
A61: Necessidades (essenciais + compromissos + provisão) ÷ renda recorrente | C61: =IFERROR((C19+C27+N(C30))/C8,0) -> 0
A62: Desejos (flexíveis) ÷ renda recorrente | C62: =IFERROR(C42/C8,0) -> 0
A63: Plano (dívidas, reserva, metas, aposentadoria) ÷ renda recorrente | C63: =IFERROR(C55/C8,0) -> 0
A64: Referência 50/30/20: 50% necessidades, 30% desejos, 20% plano. É ponto de partida, não regra.

Sheet Jun
A1: ="Orçamento de junho de "&Início!$C$5 -> Orçamento de junho de 2026
A2: Previsto: o que você planeja. Realizado: o que aconteceu, pelos extratos e faturas. O previsto vem de maio; digite por cima se mudar.
A3: Item | B3: Previsto | C3: Realizado | D3: Diferença | E3: Observação
A4: RENDA LÍQUIDA (depois de INSS e IR)
A5: ="Renda líquida de "&Início!$C$6 -> Renda líquida de Paula | B5: =Mai!B5 -> 4500 | D5: =IF(AND(B5="",C5=""),"",N(C5)-N(B5)) -> -4500
A6: ="Renda líquida de "&Início!$C$7 -> Renda líquida de Marcos | B6: =Mai!B6 -> 3500 | D6: =IF(AND(B6="",C6=""),"",N(C6)-N(B6)) -> -3500
A7: Outras rendas recorrentes (aluguel recebido, pensão) | B7: =Mai!B7 -> 0 | D7: =IF(AND(B7="",C7=""),"",N(C7)-N(B7))
A8: Renda recorrente | B8: =SUM(B5:B7) -> 8000 | C8: =SUM(C5:C7) -> 0 | D8: =N(C8)-N(B8) -> -8000
A9: Entradas não recorrentes (13º, bônus, trabalhos avulsos) | B9: =Mai!B9 -> 0 | D9: =IF(AND(B9="",C9=""),"",N(C9)-N(B9))
A10: Renda total | B10: =B8+N(B9) -> 8000 | C10: =C8+N(C9) -> 0 | D10: =N(C10)-N(B10) -> -8000
A12: ESSENCIAIS
A13: =Categorias!$C$6 -> Moradia (aluguel ou prestação, condomínio) | B13: =Mai!B13 -> 2000 | D13: =IF(AND(B13="",C13=""),"",N(C13)-N(B13)) -> -2000
A14: =Categorias!$C$7 -> Contas da casa (luz, água, gás, internet, celular) | B14: =Mai!B14 -> 450 | D14: =IF(AND(B14="",C14=""),"",N(C14)-N(B14)) -> -450
A15: =Categorias!$C$8 -> Alimentação (supermercado e feira) | B15: =Mai!B15 -> 1150 | D15: =IF(AND(B15="",C15=""),"",N(C15)-N(B15)) -> -1150
A16: =Categorias!$C$9 -> Transporte (combustível, transporte público, aplicativo) | B16: =Mai!B16 -> 350 | D16: =IF(AND(B16="",C16=""),"",N(C16)-N(B16)) -> -350
A17: =Categorias!$C$10 -> Saúde (plano, farmácia, consultas) | B17: =Mai!B17 -> 250 | D17: =IF(AND(B17="",C17=""),"",N(C17)-N(B17)) -> -250
A18: =Categorias!$C$11 -> Outros essenciais | B18: =Mai!B18 -> 0 | D18: =IF(AND(B18="",C18=""),"",N(C18)-N(B18)) -> 0
A19: Total de essenciais | B19: =SUM(B13:B18) -> 4200 | C19: =SUM(C13:C18) -> 0 | D19: =N(C19)-N(B19) -> -4200
A21: COMPROMISSOS (parcelas e mensalidades com vencimento)
A22: =Categorias!$C$12 -> Financiamento ou empréstimo | B22: =Mai!B22 -> 0 | D22: =IF(AND(B22="",C22=""),"",N(C22)-N(B22)) -> 0
A23: =Categorias!$C$13 -> Parcela do carro | B23: =Mai!B23 -> 900 | D23: =IF(AND(B23="",C23=""),"",N(C23)-N(B23)) -> -900
A24: =Categorias!$C$14 -> Escola, faculdade e cursos | B24: =Mai!B24 -> 400 | D24: =IF(AND(B24="",C24=""),"",N(C24)-N(B24)) -> -400
A25: =Categorias!$C$15 -> Seguros mensais | B25: =Mai!B25 -> 0 | D25: =IF(AND(B25="",C25=""),"",N(C25)-N(B25)) -> 0
A26: =Categorias!$C$16 -> Outras parcelas e mensalidades | B26: =Mai!B26 -> 0 | D26: =IF(AND(B26="",C26=""),"",N(C26)-N(B26)) -> 0
A27: Total de compromissos | B27: =SUM(B22:B26) -> 1300 | C27: =SUM(C22:C26) -> 0 | D27: =N(C27)-N(B27) -> -1300
A29: DESPESAS IRREGULARES
A30: Provisão mensal (aba Irregulares, total ÷ 12) | B30: =Irregulares!$C$28 -> 500 | C30: =IF(N(C8)=0,"",Irregulares!$C$28) | D30: =N(C30)-N(B30) -> -500
A31: Irregulares pagas neste mês (sai do dinheiro provisionado) | B31: =SUMIF(Irregulares!$D$6:$D$25,6,Irregulares!$C$6:$C$25) -> 0 | D31: =IF(AND(B31="",C31=""),"",N(C31)-N(B31)) -> 0 | E31: Informativo: não entra na margem, que já desconta a provisão.
A33: MARGEM DE DECISÃO (renda recorrente - essenciais - compromissos - provisão) | B33: =B8-B19-B27-N(B30) -> 2000 | C33: =IF(N(C8)=0,"",C8-C19-C27-N(C30)) | D33: =N(C33)-N(B33) -> -2000
A35: FLEXÍVEIS (saem da margem)
A36: =Categorias!$C$17 -> Restaurantes e delivery | B36: =Mai!B36 -> 150 | D36: =IF(AND(B36="",C36=""),"",N(C36)-N(B36)) -> -150
A37: =Categorias!$C$18 -> Lazer e passeios | B37: =Mai!B37 -> 120 | D37: =IF(AND(B37="",C37=""),"",N(C37)-N(B37)) -> -120
A38: =Categorias!$C$19 -> Compras (roupas, eletrônicos, casa) | B38: =Mai!B38 -> 80 | D38: =IF(AND(B38="",C38=""),"",N(C38)-N(B38)) -> -80
A39: =Categorias!$C$20 -> Assinaturas e aplicativos | B39: =Mai!B39 -> 50 | D39: =IF(AND(B39="",C39=""),"",N(C39)-N(B39)) -> -50
A40: =Categorias!$C$21 -> Cuidados pessoais | B40: =Mai!B40 -> 0 | D40: =IF(AND(B40="",C40=""),"",N(C40)-N(B40)) -> 0
A41: =Categorias!$C$22 -> Presentes e outros | B41: =Mai!B41 -> 0 | D41: =IF(AND(B41="",C41=""),"",N(C41)-N(B41)) -> 0
A42: Total de flexíveis | B42: =SUM(B36:B41) -> 400 | C42: =SUM(C36:C41) -> 0 | D42: =N(C42)-N(B42) -> -400
A43: MARGEM PARA O PLANO (margem de decisão - flexíveis) | B43: =N(B33)-B42 -> 1600 | C43: =IF(N(C8)=0,"",N(C33)-C42) | D43: =N(C43)-N(B43) -> -1600
A45: DESTINO DA MARGEM (o seu plano, na ordem do cap. 35)
A46: Pagamento extra de dívidas caras | B46: =Mai!B46 -> 0 | D46: =IF(AND(B46="",C46=""),"",N(C46)-N(B46)) -> 0
A47: Reserva de emergência | B47: =Mai!B47 -> 1000 | D47: =IF(AND(B47="",C47=""),"",N(C47)-N(B47)) -> -1000
A48: Seguro de vida e proteção | B48: =Mai!B48 -> 120 | D48: =IF(AND(B48="",C48=""),"",N(C48)-N(B48)) -> -120
A49: =IF(Metas!$B$6="","Meta 1 (aba Metas)","Meta 1: "&Metas!$B$6) -> Meta 1: Entrada do apartamento | B49: =Mai!B49 -> 480 | D49: =IF(AND(B49="",C49=""),"",N(C49)-N(B49)) -> -480
A50: =IF(Metas!$B$7="","Meta 2 (aba Metas)","Meta 2: "&Metas!$B$7) -> Meta 2: Faculdade do filho | B50: =Mai!B50 -> 0 | D50: =IF(AND(B50="",C50=""),"",N(C50)-N(B50)) -> 0
A51: =IF(Metas!$B$8="","Meta 3 (aba Metas)","Meta 3: "&Metas!$B$8) -> Meta 3 (aba Metas) | B51: =Mai!B51 -> 0 | D51: =IF(AND(B51="",C51=""),"",N(C51)-N(B51)) -> 0
A52: =IF(Metas!$B$9="","Meta 4 (aba Metas)","Meta 4: "&Metas!$B$9) -> Meta 4 (aba Metas) | B52: =Mai!B52 -> 0 | D52: =IF(AND(B52="",C52=""),"",N(C52)-N(B52)) -> 0
A53: =IF(Metas!$B$10="","Meta 5 (aba Metas)","Meta 5: "&Metas!$B$10) -> Meta 5 (aba Metas) | B53: =Mai!B53 -> 0 | D53: =IF(AND(B53="",C53=""),"",N(C53)-N(B53)) -> 0
A54: Aposentadoria (previdência ou investimentos de longo prazo) | B54: =Mai!B54 -> 0 | D54: =IF(AND(B54="",C54=""),"",N(C54)-N(B54)) -> 0
A55: Total do plano | B55: =SUM(B46:B54) -> 1600 | C55: =SUM(C46:C54) -> 0 | D55: =N(C55)-N(B55) -> -1600
A57: SALDO DO MÊS (margem para o plano - plano + entradas não recorrentes) | B57: =N(B43)-B55+N(B9) -> 0 | C57: =IF(N(C8)=0,"",N(C43)-C55+N(C9)) | D57: =N(C57)-N(B57) -> 0 | E57: Negativo: o mês fechou no vermelho. Confira com o extrato.
A59: INDICADORES DO MÊS (realizado)
A60: Taxa de poupança (plano sem seguro ÷ renda total) | C60: =IFERROR((C55-N(C48))/C10,0) -> 0
A61: Necessidades (essenciais + compromissos + provisão) ÷ renda recorrente | C61: =IFERROR((C19+C27+N(C30))/C8,0) -> 0
A62: Desejos (flexíveis) ÷ renda recorrente | C62: =IFERROR(C42/C8,0) -> 0
A63: Plano (dívidas, reserva, metas, aposentadoria) ÷ renda recorrente | C63: =IFERROR(C55/C8,0) -> 0
A64: Referência 50/30/20: 50% necessidades, 30% desejos, 20% plano. É ponto de partida, não regra.

Sheet Jul
A1: ="Orçamento de julho de "&Início!$C$5 -> Orçamento de julho de 2026
A2: Previsto: o que você planeja. Realizado: o que aconteceu, pelos extratos e faturas. O previsto vem de junho; digite por cima se mudar.
A3: Item | B3: Previsto | C3: Realizado | D3: Diferença | E3: Observação
A4: RENDA LÍQUIDA (depois de INSS e IR)
A5: ="Renda líquida de "&Início!$C$6 -> Renda líquida de Paula | B5: =Jun!B5 -> 4500 | D5: =IF(AND(B5="",C5=""),"",N(C5)-N(B5)) -> -4500
A6: ="Renda líquida de "&Início!$C$7 -> Renda líquida de Marcos | B6: =Jun!B6 -> 3500 | D6: =IF(AND(B6="",C6=""),"",N(C6)-N(B6)) -> -3500
A7: Outras rendas recorrentes (aluguel recebido, pensão) | B7: =Jun!B7 -> 0 | D7: =IF(AND(B7="",C7=""),"",N(C7)-N(B7))
A8: Renda recorrente | B8: =SUM(B5:B7) -> 8000 | C8: =SUM(C5:C7) -> 0 | D8: =N(C8)-N(B8) -> -8000
A9: Entradas não recorrentes (13º, bônus, trabalhos avulsos) | B9: =Jun!B9 -> 0 | D9: =IF(AND(B9="",C9=""),"",N(C9)-N(B9))
A10: Renda total | B10: =B8+N(B9) -> 8000 | C10: =C8+N(C9) -> 0 | D10: =N(C10)-N(B10) -> -8000
A12: ESSENCIAIS
A13: =Categorias!$C$6 -> Moradia (aluguel ou prestação, condomínio) | B13: =Jun!B13 -> 2000 | D13: =IF(AND(B13="",C13=""),"",N(C13)-N(B13)) -> -2000
A14: =Categorias!$C$7 -> Contas da casa (luz, água, gás, internet, celular) | B14: =Jun!B14 -> 450 | D14: =IF(AND(B14="",C14=""),"",N(C14)-N(B14)) -> -450
A15: =Categorias!$C$8 -> Alimentação (supermercado e feira) | B15: =Jun!B15 -> 1150 | D15: =IF(AND(B15="",C15=""),"",N(C15)-N(B15)) -> -1150
A16: =Categorias!$C$9 -> Transporte (combustível, transporte público, aplicativo) | B16: =Jun!B16 -> 350 | D16: =IF(AND(B16="",C16=""),"",N(C16)-N(B16)) -> -350
A17: =Categorias!$C$10 -> Saúde (plano, farmácia, consultas) | B17: =Jun!B17 -> 250 | D17: =IF(AND(B17="",C17=""),"",N(C17)-N(B17)) -> -250
A18: =Categorias!$C$11 -> Outros essenciais | B18: =Jun!B18 -> 0 | D18: =IF(AND(B18="",C18=""),"",N(C18)-N(B18)) -> 0
A19: Total de essenciais | B19: =SUM(B13:B18) -> 4200 | C19: =SUM(C13:C18) -> 0 | D19: =N(C19)-N(B19) -> -4200
A21: COMPROMISSOS (parcelas e mensalidades com vencimento)
A22: =Categorias!$C$12 -> Financiamento ou empréstimo | B22: =Jun!B22 -> 0 | D22: =IF(AND(B22="",C22=""),"",N(C22)-N(B22)) -> 0
A23: =Categorias!$C$13 -> Parcela do carro | B23: =Jun!B23 -> 900 | D23: =IF(AND(B23="",C23=""),"",N(C23)-N(B23)) -> -900
A24: =Categorias!$C$14 -> Escola, faculdade e cursos | B24: =Jun!B24 -> 400 | D24: =IF(AND(B24="",C24=""),"",N(C24)-N(B24)) -> -400
A25: =Categorias!$C$15 -> Seguros mensais | B25: =Jun!B25 -> 0 | D25: =IF(AND(B25="",C25=""),"",N(C25)-N(B25)) -> 0
A26: =Categorias!$C$16 -> Outras parcelas e mensalidades | B26: =Jun!B26 -> 0 | D26: =IF(AND(B26="",C26=""),"",N(C26)-N(B26)) -> 0
A27: Total de compromissos | B27: =SUM(B22:B26) -> 1300 | C27: =SUM(C22:C26) -> 0 | D27: =N(C27)-N(B27) -> -1300
A29: DESPESAS IRREGULARES
A30: Provisão mensal (aba Irregulares, total ÷ 12) | B30: =Irregulares!$C$28 -> 500 | C30: =IF(N(C8)=0,"",Irregulares!$C$28) | D30: =N(C30)-N(B30) -> -500
A31: Irregulares pagas neste mês (sai do dinheiro provisionado) | B31: =SUMIF(Irregulares!$D$6:$D$25,7,Irregulares!$C$6:$C$25) -> 0 | D31: =IF(AND(B31="",C31=""),"",N(C31)-N(B31)) -> 0 | E31: Informativo: não entra na margem, que já desconta a provisão.
A33: MARGEM DE DECISÃO (renda recorrente - essenciais - compromissos - provisão) | B33: =B8-B19-B27-N(B30) -> 2000 | C33: =IF(N(C8)=0,"",C8-C19-C27-N(C30)) | D33: =N(C33)-N(B33) -> -2000
A35: FLEXÍVEIS (saem da margem)
A36: =Categorias!$C$17 -> Restaurantes e delivery | B36: =Jun!B36 -> 150 | D36: =IF(AND(B36="",C36=""),"",N(C36)-N(B36)) -> -150
A37: =Categorias!$C$18 -> Lazer e passeios | B37: =Jun!B37 -> 120 | D37: =IF(AND(B37="",C37=""),"",N(C37)-N(B37)) -> -120
A38: =Categorias!$C$19 -> Compras (roupas, eletrônicos, casa) | B38: =Jun!B38 -> 80 | D38: =IF(AND(B38="",C38=""),"",N(C38)-N(B38)) -> -80
A39: =Categorias!$C$20 -> Assinaturas e aplicativos | B39: =Jun!B39 -> 50 | D39: =IF(AND(B39="",C39=""),"",N(C39)-N(B39)) -> -50
A40: =Categorias!$C$21 -> Cuidados pessoais | B40: =Jun!B40 -> 0 | D40: =IF(AND(B40="",C40=""),"",N(C40)-N(B40)) -> 0
A41: =Categorias!$C$22 -> Presentes e outros | B41: =Jun!B41 -> 0 | D41: =IF(AND(B41="",C41=""),"",N(C41)-N(B41)) -> 0
A42: Total de flexíveis | B42: =SUM(B36:B41) -> 400 | C42: =SUM(C36:C41) -> 0 | D42: =N(C42)-N(B42) -> -400
A43: MARGEM PARA O PLANO (margem de decisão - flexíveis) | B43: =N(B33)-B42 -> 1600 | C43: =IF(N(C8)=0,"",N(C33)-C42) | D43: =N(C43)-N(B43) -> -1600
A45: DESTINO DA MARGEM (o seu plano, na ordem do cap. 35)
A46: Pagamento extra de dívidas caras | B46: =Jun!B46 -> 0 | D46: =IF(AND(B46="",C46=""),"",N(C46)-N(B46)) -> 0
A47: Reserva de emergência | B47: =Jun!B47 -> 1000 | D47: =IF(AND(B47="",C47=""),"",N(C47)-N(B47)) -> -1000
A48: Seguro de vida e proteção | B48: =Jun!B48 -> 120 | D48: =IF(AND(B48="",C48=""),"",N(C48)-N(B48)) -> -120
A49: =IF(Metas!$B$6="","Meta 1 (aba Metas)","Meta 1: "&Metas!$B$6) -> Meta 1: Entrada do apartamento | B49: =Jun!B49 -> 480 | D49: =IF(AND(B49="",C49=""),"",N(C49)-N(B49)) -> -480
A50: =IF(Metas!$B$7="","Meta 2 (aba Metas)","Meta 2: "&Metas!$B$7) -> Meta 2: Faculdade do filho | B50: =Jun!B50 -> 0 | D50: =IF(AND(B50="",C50=""),"",N(C50)-N(B50)) -> 0
A51: =IF(Metas!$B$8="","Meta 3 (aba Metas)","Meta 3: "&Metas!$B$8) -> Meta 3 (aba Metas) | B51: =Jun!B51 -> 0 | D51: =IF(AND(B51="",C51=""),"",N(C51)-N(B51)) -> 0
A52: =IF(Metas!$B$9="","Meta 4 (aba Metas)","Meta 4: "&Metas!$B$9) -> Meta 4 (aba Metas) | B52: =Jun!B52 -> 0 | D52: =IF(AND(B52="",C52=""),"",N(C52)-N(B52)) -> 0
A53: =IF(Metas!$B$10="","Meta 5 (aba Metas)","Meta 5: "&Metas!$B$10) -> Meta 5 (aba Metas) | B53: =Jun!B53 -> 0 | D53: =IF(AND(B53="",C53=""),"",N(C53)-N(B53)) -> 0
A54: Aposentadoria (previdência ou investimentos de longo prazo) | B54: =Jun!B54 -> 0 | D54: =IF(AND(B54="",C54=""),"",N(C54)-N(B54)) -> 0
A55: Total do plano | B55: =SUM(B46:B54) -> 1600 | C55: =SUM(C46:C54) -> 0 | D55: =N(C55)-N(B55) -> -1600
A57: SALDO DO MÊS (margem para o plano - plano + entradas não recorrentes) | B57: =N(B43)-B55+N(B9) -> 0 | C57: =IF(N(C8)=0,"",N(C43)-C55+N(C9)) | D57: =N(C57)-N(B57) -> 0 | E57: Negativo: o mês fechou no vermelho. Confira com o extrato.
A59: INDICADORES DO MÊS (realizado)
A60: Taxa de poupança (plano sem seguro ÷ renda total) | C60: =IFERROR((C55-N(C48))/C10,0) -> 0
A61: Necessidades (essenciais + compromissos + provisão) ÷ renda recorrente | C61: =IFERROR((C19+C27+N(C30))/C8,0) -> 0
A62: Desejos (flexíveis) ÷ renda recorrente | C62: =IFERROR(C42/C8,0) -> 0
A63: Plano (dívidas, reserva, metas, aposentadoria) ÷ renda recorrente | C63: =IFERROR(C55/C8,0) -> 0
A64: Referência 50/30/20: 50% necessidades, 30% desejos, 20% plano. É ponto de partida, não regra.

Sheet Ago
A1: ="Orçamento de agosto de "&Início!$C$5 -> Orçamento de agosto de 2026
A2: Previsto: o que você planeja. Realizado: o que aconteceu, pelos extratos e faturas. O previsto vem de julho; digite por cima se mudar.
A3: Item | B3: Previsto | C3: Realizado | D3: Diferença | E3: Observação
A4: RENDA LÍQUIDA (depois de INSS e IR)
A5: ="Renda líquida de "&Início!$C$6 -> Renda líquida de Paula | B5: =Jul!B5 -> 4500 | D5: =IF(AND(B5="",C5=""),"",N(C5)-N(B5)) -> -4500
A6: ="Renda líquida de "&Início!$C$7 -> Renda líquida de Marcos | B6: =Jul!B6 -> 3500 | D6: =IF(AND(B6="",C6=""),"",N(C6)-N(B6)) -> -3500
A7: Outras rendas recorrentes (aluguel recebido, pensão) | B7: =Jul!B7 -> 0 | D7: =IF(AND(B7="",C7=""),"",N(C7)-N(B7))
A8: Renda recorrente | B8: =SUM(B5:B7) -> 8000 | C8: =SUM(C5:C7) -> 0 | D8: =N(C8)-N(B8) -> -8000
A9: Entradas não recorrentes (13º, bônus, trabalhos avulsos) | B9: =Jul!B9 -> 0 | D9: =IF(AND(B9="",C9=""),"",N(C9)-N(B9))
A10: Renda total | B10: =B8+N(B9) -> 8000 | C10: =C8+N(C9) -> 0 | D10: =N(C10)-N(B10) -> -8000
A12: ESSENCIAIS
A13: =Categorias!$C$6 -> Moradia (aluguel ou prestação, condomínio) | B13: =Jul!B13 -> 2000 | D13: =IF(AND(B13="",C13=""),"",N(C13)-N(B13)) -> -2000
A14: =Categorias!$C$7 -> Contas da casa (luz, água, gás, internet, celular) | B14: =Jul!B14 -> 450 | D14: =IF(AND(B14="",C14=""),"",N(C14)-N(B14)) -> -450
A15: =Categorias!$C$8 -> Alimentação (supermercado e feira) | B15: =Jul!B15 -> 1150 | D15: =IF(AND(B15="",C15=""),"",N(C15)-N(B15)) -> -1150
A16: =Categorias!$C$9 -> Transporte (combustível, transporte público, aplicativo) | B16: =Jul!B16 -> 350 | D16: =IF(AND(B16="",C16=""),"",N(C16)-N(B16)) -> -350
A17: =Categorias!$C$10 -> Saúde (plano, farmácia, consultas) | B17: =Jul!B17 -> 250 | D17: =IF(AND(B17="",C17=""),"",N(C17)-N(B17)) -> -250
A18: =Categorias!$C$11 -> Outros essenciais | B18: =Jul!B18 -> 0 | D18: =IF(AND(B18="",C18=""),"",N(C18)-N(B18)) -> 0
A19: Total de essenciais | B19: =SUM(B13:B18) -> 4200 | C19: =SUM(C13:C18) -> 0 | D19: =N(C19)-N(B19) -> -4200
A21: COMPROMISSOS (parcelas e mensalidades com vencimento)
A22: =Categorias!$C$12 -> Financiamento ou empréstimo | B22: =Jul!B22 -> 0 | D22: =IF(AND(B22="",C22=""),"",N(C22)-N(B22)) -> 0
A23: =Categorias!$C$13 -> Parcela do carro | B23: =Jul!B23 -> 900 | D23: =IF(AND(B23="",C23=""),"",N(C23)-N(B23)) -> -900
A24: =Categorias!$C$14 -> Escola, faculdade e cursos | B24: =Jul!B24 -> 400 | D24: =IF(AND(B24="",C24=""),"",N(C24)-N(B24)) -> -400
A25: =Categorias!$C$15 -> Seguros mensais | B25: =Jul!B25 -> 0 | D25: =IF(AND(B25="",C25=""),"",N(C25)-N(B25)) -> 0
A26: =Categorias!$C$16 -> Outras parcelas e mensalidades | B26: =Jul!B26 -> 0 | D26: =IF(AND(B26="",C26=""),"",N(C26)-N(B26)) -> 0
A27: Total de compromissos | B27: =SUM(B22:B26) -> 1300 | C27: =SUM(C22:C26) -> 0 | D27: =N(C27)-N(B27) -> -1300
A29: DESPESAS IRREGULARES
A30: Provisão mensal (aba Irregulares, total ÷ 12) | B30: =Irregulares!$C$28 -> 500 | C30: =IF(N(C8)=0,"",Irregulares!$C$28) | D30: =N(C30)-N(B30) -> -500
A31: Irregulares pagas neste mês (sai do dinheiro provisionado) | B31: =SUMIF(Irregulares!$D$6:$D$25,8,Irregulares!$C$6:$C$25) -> 0 | D31: =IF(AND(B31="",C31=""),"",N(C31)-N(B31)) -> 0 | E31: Informativo: não entra na margem, que já desconta a provisão.
A33: MARGEM DE DECISÃO (renda recorrente - essenciais - compromissos - provisão) | B33: =B8-B19-B27-N(B30) -> 2000 | C33: =IF(N(C8)=0,"",C8-C19-C27-N(C30)) | D33: =N(C33)-N(B33) -> -2000
A35: FLEXÍVEIS (saem da margem)
A36: =Categorias!$C$17 -> Restaurantes e delivery | B36: =Jul!B36 -> 150 | D36: =IF(AND(B36="",C36=""),"",N(C36)-N(B36)) -> -150
A37: =Categorias!$C$18 -> Lazer e passeios | B37: =Jul!B37 -> 120 | D37: =IF(AND(B37="",C37=""),"",N(C37)-N(B37)) -> -120
A38: =Categorias!$C$19 -> Compras (roupas, eletrônicos, casa) | B38: =Jul!B38 -> 80 | D38: =IF(AND(B38="",C38=""),"",N(C38)-N(B38)) -> -80
A39: =Categorias!$C$20 -> Assinaturas e aplicativos | B39: =Jul!B39 -> 50 | D39: =IF(AND(B39="",C39=""),"",N(C39)-N(B39)) -> -50
A40: =Categorias!$C$21 -> Cuidados pessoais | B40: =Jul!B40 -> 0 | D40: =IF(AND(B40="",C40=""),"",N(C40)-N(B40)) -> 0
A41: =Categorias!$C$22 -> Presentes e outros | B41: =Jul!B41 -> 0 | D41: =IF(AND(B41="",C41=""),"",N(C41)-N(B41)) -> 0
A42: Total de flexíveis | B42: =SUM(B36:B41) -> 400 | C42: =SUM(C36:C41) -> 0 | D42: =N(C42)-N(B42) -> -400
A43: MARGEM PARA O PLANO (margem de decisão - flexíveis) | B43: =N(B33)-B42 -> 1600 | C43: =IF(N(C8)=0,"",N(C33)-C42) | D43: =N(C43)-N(B43) -> -1600
A45: DESTINO DA MARGEM (o seu plano, na ordem do cap. 35)
A46: Pagamento extra de dívidas caras | B46: =Jul!B46 -> 0 | D46: =IF(AND(B46="",C46=""),"",N(C46)-N(B46)) -> 0
A47: Reserva de emergência | B47: =Jul!B47 -> 1000 | D47: =IF(AND(B47="",C47=""),"",N(C47)-N(B47)) -> -1000
A48: Seguro de vida e proteção | B48: =Jul!B48 -> 120 | D48: =IF(AND(B48="",C48=""),"",N(C48)-N(B48)) -> -120
A49: =IF(Metas!$B$6="","Meta 1 (aba Metas)","Meta 1: "&Metas!$B$6) -> Meta 1: Entrada do apartamento | B49: =Jul!B49 -> 480 | D49: =IF(AND(B49="",C49=""),"",N(C49)-N(B49)) -> -480
A50: =IF(Metas!$B$7="","Meta 2 (aba Metas)","Meta 2: "&Metas!$B$7) -> Meta 2: Faculdade do filho | B50: =Jul!B50 -> 0 | D50: =IF(AND(B50="",C50=""),"",N(C50)-N(B50)) -> 0
A51: =IF(Metas!$B$8="","Meta 3 (aba Metas)","Meta 3: "&Metas!$B$8) -> Meta 3 (aba Metas) | B51: =Jul!B51 -> 0 | D51: =IF(AND(B51="",C51=""),"",N(C51)-N(B51)) -> 0
A52: =IF(Metas!$B$9="","Meta 4 (aba Metas)","Meta 4: "&Metas!$B$9) -> Meta 4 (aba Metas) | B52: =Jul!B52 -> 0 | D52: =IF(AND(B52="",C52=""),"",N(C52)-N(B52)) -> 0
A53: =IF(Metas!$B$10="","Meta 5 (aba Metas)","Meta 5: "&Metas!$B$10) -> Meta 5 (aba Metas) | B53: =Jul!B53 -> 0 | D53: =IF(AND(B53="",C53=""),"",N(C53)-N(B53)) -> 0
A54: Aposentadoria (previdência ou investimentos de longo prazo) | B54: =Jul!B54 -> 0 | D54: =IF(AND(B54="",C54=""),"",N(C54)-N(B54)) -> 0
A55: Total do plano | B55: =SUM(B46:B54) -> 1600 | C55: =SUM(C46:C54) -> 0 | D55: =N(C55)-N(B55) -> -1600
A57: SALDO DO MÊS (margem para o plano - plano + entradas não recorrentes) | B57: =N(B43)-B55+N(B9) -> 0 | C57: =IF(N(C8)=0,"",N(C43)-C55+N(C9)) | D57: =N(C57)-N(B57) -> 0 | E57: Negativo: o mês fechou no vermelho. Confira com o extrato.
A59: INDICADORES DO MÊS (realizado)
A60: Taxa de poupança (plano sem seguro ÷ renda total) | C60: =IFERROR((C55-N(C48))/C10,0) -> 0
A61: Necessidades (essenciais + compromissos + provisão) ÷ renda recorrente | C61: =IFERROR((C19+C27+N(C30))/C8,0) -> 0
A62: Desejos (flexíveis) ÷ renda recorrente | C62: =IFERROR(C42/C8,0) -> 0
A63: Plano (dívidas, reserva, metas, aposentadoria) ÷ renda recorrente | C63: =IFERROR(C55/C8,0) -> 0
A64: Referência 50/30/20: 50% necessidades, 30% desejos, 20% plano. É ponto de partida, não regra.

Sheet Set
A1: ="Orçamento de setembro de "&Início!$C$5 -> Orçamento de setembro de 2026
A2: Previsto: o que você planeja. Realizado: o que aconteceu, pelos extratos e faturas. O previsto vem de agosto; digite por cima se mudar.
A3: Item | B3: Previsto | C3: Realizado | D3: Diferença | E3: Observação
A4: RENDA LÍQUIDA (depois de INSS e IR)
A5: ="Renda líquida de "&Início!$C$6 -> Renda líquida de Paula | B5: =Ago!B5 -> 4500 | D5: =IF(AND(B5="",C5=""),"",N(C5)-N(B5)) -> -4500
A6: ="Renda líquida de "&Início!$C$7 -> Renda líquida de Marcos | B6: =Ago!B6 -> 3500 | D6: =IF(AND(B6="",C6=""),"",N(C6)-N(B6)) -> -3500
A7: Outras rendas recorrentes (aluguel recebido, pensão) | B7: =Ago!B7 -> 0 | D7: =IF(AND(B7="",C7=""),"",N(C7)-N(B7))
A8: Renda recorrente | B8: =SUM(B5:B7) -> 8000 | C8: =SUM(C5:C7) -> 0 | D8: =N(C8)-N(B8) -> -8000
A9: Entradas não recorrentes (13º, bônus, trabalhos avulsos) | B9: =Ago!B9 -> 0 | D9: =IF(AND(B9="",C9=""),"",N(C9)-N(B9))
A10: Renda total | B10: =B8+N(B9) -> 8000 | C10: =C8+N(C9) -> 0 | D10: =N(C10)-N(B10) -> -8000
A12: ESSENCIAIS
A13: =Categorias!$C$6 -> Moradia (aluguel ou prestação, condomínio) | B13: =Ago!B13 -> 2000 | D13: =IF(AND(B13="",C13=""),"",N(C13)-N(B13)) -> -2000
A14: =Categorias!$C$7 -> Contas da casa (luz, água, gás, internet, celular) | B14: =Ago!B14 -> 450 | D14: =IF(AND(B14="",C14=""),"",N(C14)-N(B14)) -> -450
A15: =Categorias!$C$8 -> Alimentação (supermercado e feira) | B15: =Ago!B15 -> 1150 | D15: =IF(AND(B15="",C15=""),"",N(C15)-N(B15)) -> -1150
A16: =Categorias!$C$9 -> Transporte (combustível, transporte público, aplicativo) | B16: =Ago!B16 -> 350 | D16: =IF(AND(B16="",C16=""),"",N(C16)-N(B16)) -> -350
A17: =Categorias!$C$10 -> Saúde (plano, farmácia, consultas) | B17: =Ago!B17 -> 250 | D17: =IF(AND(B17="",C17=""),"",N(C17)-N(B17)) -> -250
A18: =Categorias!$C$11 -> Outros essenciais | B18: =Ago!B18 -> 0 | D18: =IF(AND(B18="",C18=""),"",N(C18)-N(B18)) -> 0
A19: Total de essenciais | B19: =SUM(B13:B18) -> 4200 | C19: =SUM(C13:C18) -> 0 | D19: =N(C19)-N(B19) -> -4200
A21: COMPROMISSOS (parcelas e mensalidades com vencimento)
A22: =Categorias!$C$12 -> Financiamento ou empréstimo | B22: =Ago!B22 -> 0 | D22: =IF(AND(B22="",C22=""),"",N(C22)-N(B22)) -> 0
A23: =Categorias!$C$13 -> Parcela do carro | B23: =Ago!B23 -> 900 | D23: =IF(AND(B23="",C23=""),"",N(C23)-N(B23)) -> -900
A24: =Categorias!$C$14 -> Escola, faculdade e cursos | B24: =Ago!B24 -> 400 | D24: =IF(AND(B24="",C24=""),"",N(C24)-N(B24)) -> -400
A25: =Categorias!$C$15 -> Seguros mensais | B25: =Ago!B25 -> 0 | D25: =IF(AND(B25="",C25=""),"",N(C25)-N(B25)) -> 0
A26: =Categorias!$C$16 -> Outras parcelas e mensalidades | B26: =Ago!B26 -> 0 | D26: =IF(AND(B26="",C26=""),"",N(C26)-N(B26)) -> 0
A27: Total de compromissos | B27: =SUM(B22:B26) -> 1300 | C27: =SUM(C22:C26) -> 0 | D27: =N(C27)-N(B27) -> -1300
A29: DESPESAS IRREGULARES
A30: Provisão mensal (aba Irregulares, total ÷ 12) | B30: =Irregulares!$C$28 -> 500 | C30: =IF(N(C8)=0,"",Irregulares!$C$28) | D30: =N(C30)-N(B30) -> -500
A31: Irregulares pagas neste mês (sai do dinheiro provisionado) | B31: =SUMIF(Irregulares!$D$6:$D$25,9,Irregulares!$C$6:$C$25) -> 0 | D31: =IF(AND(B31="",C31=""),"",N(C31)-N(B31)) -> 0 | E31: Informativo: não entra na margem, que já desconta a provisão.
A33: MARGEM DE DECISÃO (renda recorrente - essenciais - compromissos - provisão) | B33: =B8-B19-B27-N(B30) -> 2000 | C33: =IF(N(C8)=0,"",C8-C19-C27-N(C30)) | D33: =N(C33)-N(B33) -> -2000
A35: FLEXÍVEIS (saem da margem)
A36: =Categorias!$C$17 -> Restaurantes e delivery | B36: =Ago!B36 -> 150 | D36: =IF(AND(B36="",C36=""),"",N(C36)-N(B36)) -> -150
A37: =Categorias!$C$18 -> Lazer e passeios | B37: =Ago!B37 -> 120 | D37: =IF(AND(B37="",C37=""),"",N(C37)-N(B37)) -> -120
A38: =Categorias!$C$19 -> Compras (roupas, eletrônicos, casa) | B38: =Ago!B38 -> 80 | D38: =IF(AND(B38="",C38=""),"",N(C38)-N(B38)) -> -80
A39: =Categorias!$C$20 -> Assinaturas e aplicativos | B39: =Ago!B39 -> 50 | D39: =IF(AND(B39="",C39=""),"",N(C39)-N(B39)) -> -50
A40: =Categorias!$C$21 -> Cuidados pessoais | B40: =Ago!B40 -> 0 | D40: =IF(AND(B40="",C40=""),"",N(C40)-N(B40)) -> 0
A41: =Categorias!$C$22 -> Presentes e outros | B41: =Ago!B41 -> 0 | D41: =IF(AND(B41="",C41=""),"",N(C41)-N(B41)) -> 0
A42: Total de flexíveis | B42: =SUM(B36:B41) -> 400 | C42: =SUM(C36:C41) -> 0 | D42: =N(C42)-N(B42) -> -400
A43: MARGEM PARA O PLANO (margem de decisão - flexíveis) | B43: =N(B33)-B42 -> 1600 | C43: =IF(N(C8)=0,"",N(C33)-C42) | D43: =N(C43)-N(B43) -> -1600
A45: DESTINO DA MARGEM (o seu plano, na ordem do cap. 35)
A46: Pagamento extra de dívidas caras | B46: =Ago!B46 -> 0 | D46: =IF(AND(B46="",C46=""),"",N(C46)-N(B46)) -> 0
A47: Reserva de emergência | B47: =Ago!B47 -> 1000 | D47: =IF(AND(B47="",C47=""),"",N(C47)-N(B47)) -> -1000
A48: Seguro de vida e proteção | B48: =Ago!B48 -> 120 | D48: =IF(AND(B48="",C48=""),"",N(C48)-N(B48)) -> -120
A49: =IF(Metas!$B$6="","Meta 1 (aba Metas)","Meta 1: "&Metas!$B$6) -> Meta 1: Entrada do apartamento | B49: =Ago!B49 -> 480 | D49: =IF(AND(B49="",C49=""),"",N(C49)-N(B49)) -> -480
A50: =IF(Metas!$B$7="","Meta 2 (aba Metas)","Meta 2: "&Metas!$B$7) -> Meta 2: Faculdade do filho | B50: =Ago!B50 -> 0 | D50: =IF(AND(B50="",C50=""),"",N(C50)-N(B50)) -> 0
A51: =IF(Metas!$B$8="","Meta 3 (aba Metas)","Meta 3: "&Metas!$B$8) -> Meta 3 (aba Metas) | B51: =Ago!B51 -> 0 | D51: =IF(AND(B51="",C51=""),"",N(C51)-N(B51)) -> 0
A52: =IF(Metas!$B$9="","Meta 4 (aba Metas)","Meta 4: "&Metas!$B$9) -> Meta 4 (aba Metas) | B52: =Ago!B52 -> 0 | D52: =IF(AND(B52="",C52=""),"",N(C52)-N(B52)) -> 0
A53: =IF(Metas!$B$10="","Meta 5 (aba Metas)","Meta 5: "&Metas!$B$10) -> Meta 5 (aba Metas) | B53: =Ago!B53 -> 0 | D53: =IF(AND(B53="",C53=""),"",N(C53)-N(B53)) -> 0
A54: Aposentadoria (previdência ou investimentos de longo prazo) | B54: =Ago!B54 -> 0 | D54: =IF(AND(B54="",C54=""),"",N(C54)-N(B54)) -> 0
A55: Total do plano | B55: =SUM(B46:B54) -> 1600 | C55: =SUM(C46:C54) -> 0 | D55: =N(C55)-N(B55) -> -1600
A57: SALDO DO MÊS (margem para o plano - plano + entradas não recorrentes) | B57: =N(B43)-B55+N(B9) -> 0 | C57: =IF(N(C8)=0,"",N(C43)-C55+N(C9)) | D57: =N(C57)-N(B57) -> 0 | E57: Negativo: o mês fechou no vermelho. Confira com o extrato.
A59: INDICADORES DO MÊS (realizado)
A60: Taxa de poupança (plano sem seguro ÷ renda total) | C60: =IFERROR((C55-N(C48))/C10,0) -> 0
A61: Necessidades (essenciais + compromissos + provisão) ÷ renda recorrente | C61: =IFERROR((C19+C27+N(C30))/C8,0) -> 0
A62: Desejos (flexíveis) ÷ renda recorrente | C62: =IFERROR(C42/C8,0) -> 0
A63: Plano (dívidas, reserva, metas, aposentadoria) ÷ renda recorrente | C63: =IFERROR(C55/C8,0) -> 0
A64: Referência 50/30/20: 50% necessidades, 30% desejos, 20% plano. É ponto de partida, não regra.

Sheet Out
A1: ="Orçamento de outubro de "&Início!$C$5 -> Orçamento de outubro de 2026
A2: Previsto: o que você planeja. Realizado: o que aconteceu, pelos extratos e faturas. O previsto vem de setembro; digite por cima se mudar.
A3: Item | B3: Previsto | C3: Realizado | D3: Diferença | E3: Observação
A4: RENDA LÍQUIDA (depois de INSS e IR)
A5: ="Renda líquida de "&Início!$C$6 -> Renda líquida de Paula | B5: =Set!B5 -> 4500 | D5: =IF(AND(B5="",C5=""),"",N(C5)-N(B5)) -> -4500
A6: ="Renda líquida de "&Início!$C$7 -> Renda líquida de Marcos | B6: =Set!B6 -> 3500 | D6: =IF(AND(B6="",C6=""),"",N(C6)-N(B6)) -> -3500
A7: Outras rendas recorrentes (aluguel recebido, pensão) | B7: =Set!B7 -> 0 | D7: =IF(AND(B7="",C7=""),"",N(C7)-N(B7))
A8: Renda recorrente | B8: =SUM(B5:B7) -> 8000 | C8: =SUM(C5:C7) -> 0 | D8: =N(C8)-N(B8) -> -8000
A9: Entradas não recorrentes (13º, bônus, trabalhos avulsos) | B9: =Set!B9 -> 0 | D9: =IF(AND(B9="",C9=""),"",N(C9)-N(B9))
A10: Renda total | B10: =B8+N(B9) -> 8000 | C10: =C8+N(C9) -> 0 | D10: =N(C10)-N(B10) -> -8000
A12: ESSENCIAIS
A13: =Categorias!$C$6 -> Moradia (aluguel ou prestação, condomínio) | B13: =Set!B13 -> 2000 | D13: =IF(AND(B13="",C13=""),"",N(C13)-N(B13)) -> -2000
A14: =Categorias!$C$7 -> Contas da casa (luz, água, gás, internet, celular) | B14: =Set!B14 -> 450 | D14: =IF(AND(B14="",C14=""),"",N(C14)-N(B14)) -> -450
A15: =Categorias!$C$8 -> Alimentação (supermercado e feira) | B15: =Set!B15 -> 1150 | D15: =IF(AND(B15="",C15=""),"",N(C15)-N(B15)) -> -1150
A16: =Categorias!$C$9 -> Transporte (combustível, transporte público, aplicativo) | B16: =Set!B16 -> 350 | D16: =IF(AND(B16="",C16=""),"",N(C16)-N(B16)) -> -350
A17: =Categorias!$C$10 -> Saúde (plano, farmácia, consultas) | B17: =Set!B17 -> 250 | D17: =IF(AND(B17="",C17=""),"",N(C17)-N(B17)) -> -250
A18: =Categorias!$C$11 -> Outros essenciais | B18: =Set!B18 -> 0 | D18: =IF(AND(B18="",C18=""),"",N(C18)-N(B18)) -> 0
A19: Total de essenciais | B19: =SUM(B13:B18) -> 4200 | C19: =SUM(C13:C18) -> 0 | D19: =N(C19)-N(B19) -> -4200
A21: COMPROMISSOS (parcelas e mensalidades com vencimento)
A22: =Categorias!$C$12 -> Financiamento ou empréstimo | B22: =Set!B22 -> 0 | D22: =IF(AND(B22="",C22=""),"",N(C22)-N(B22)) -> 0
A23: =Categorias!$C$13 -> Parcela do carro | B23: =Set!B23 -> 900 | D23: =IF(AND(B23="",C23=""),"",N(C23)-N(B23)) -> -900
A24: =Categorias!$C$14 -> Escola, faculdade e cursos | B24: =Set!B24 -> 400 | D24: =IF(AND(B24="",C24=""),"",N(C24)-N(B24)) -> -400
A25: =Categorias!$C$15 -> Seguros mensais | B25: =Set!B25 -> 0 | D25: =IF(AND(B25="",C25=""),"",N(C25)-N(B25)) -> 0
A26: =Categorias!$C$16 -> Outras parcelas e mensalidades | B26: =Set!B26 -> 0 | D26: =IF(AND(B26="",C26=""),"",N(C26)-N(B26)) -> 0
A27: Total de compromissos | B27: =SUM(B22:B26) -> 1300 | C27: =SUM(C22:C26) -> 0 | D27: =N(C27)-N(B27) -> -1300
A29: DESPESAS IRREGULARES
A30: Provisão mensal (aba Irregulares, total ÷ 12) | B30: =Irregulares!$C$28 -> 500 | C30: =IF(N(C8)=0,"",Irregulares!$C$28) | D30: =N(C30)-N(B30) -> -500
A31: Irregulares pagas neste mês (sai do dinheiro provisionado) | B31: =SUMIF(Irregulares!$D$6:$D$25,10,Irregulares!$C$6:$C$25) -> 0 | D31: =IF(AND(B31="",C31=""),"",N(C31)-N(B31)) -> 0 | E31: Informativo: não entra na margem, que já desconta a provisão.
A33: MARGEM DE DECISÃO (renda recorrente - essenciais - compromissos - provisão) | B33: =B8-B19-B27-N(B30) -> 2000 | C33: =IF(N(C8)=0,"",C8-C19-C27-N(C30)) | D33: =N(C33)-N(B33) -> -2000
A35: FLEXÍVEIS (saem da margem)
A36: =Categorias!$C$17 -> Restaurantes e delivery | B36: =Set!B36 -> 150 | D36: =IF(AND(B36="",C36=""),"",N(C36)-N(B36)) -> -150
A37: =Categorias!$C$18 -> Lazer e passeios | B37: =Set!B37 -> 120 | D37: =IF(AND(B37="",C37=""),"",N(C37)-N(B37)) -> -120
A38: =Categorias!$C$19 -> Compras (roupas, eletrônicos, casa) | B38: =Set!B38 -> 80 | D38: =IF(AND(B38="",C38=""),"",N(C38)-N(B38)) -> -80
A39: =Categorias!$C$20 -> Assinaturas e aplicativos | B39: =Set!B39 -> 50 | D39: =IF(AND(B39="",C39=""),"",N(C39)-N(B39)) -> -50
A40: =Categorias!$C$21 -> Cuidados pessoais | B40: =Set!B40 -> 0 | D40: =IF(AND(B40="",C40=""),"",N(C40)-N(B40)) -> 0
A41: =Categorias!$C$22 -> Presentes e outros | B41: =Set!B41 -> 0 | D41: =IF(AND(B41="",C41=""),"",N(C41)-N(B41)) -> 0
A42: Total de flexíveis | B42: =SUM(B36:B41) -> 400 | C42: =SUM(C36:C41) -> 0 | D42: =N(C42)-N(B42) -> -400
A43: MARGEM PARA O PLANO (margem de decisão - flexíveis) | B43: =N(B33)-B42 -> 1600 | C43: =IF(N(C8)=0,"",N(C33)-C42) | D43: =N(C43)-N(B43) -> -1600
A45: DESTINO DA MARGEM (o seu plano, na ordem do cap. 35)
A46: Pagamento extra de dívidas caras | B46: =Set!B46 -> 0 | D46: =IF(AND(B46="",C46=""),"",N(C46)-N(B46)) -> 0
A47: Reserva de emergência | B47: =Set!B47 -> 1000 | D47: =IF(AND(B47="",C47=""),"",N(C47)-N(B47)) -> -1000
A48: Seguro de vida e proteção | B48: =Set!B48 -> 120 | D48: =IF(AND(B48="",C48=""),"",N(C48)-N(B48)) -> -120
A49: =IF(Metas!$B$6="","Meta 1 (aba Metas)","Meta 1: "&Metas!$B$6) -> Meta 1: Entrada do apartamento | B49: =Set!B49 -> 480 | D49: =IF(AND(B49="",C49=""),"",N(C49)-N(B49)) -> -480
A50: =IF(Metas!$B$7="","Meta 2 (aba Metas)","Meta 2: "&Metas!$B$7) -> Meta 2: Faculdade do filho | B50: =Set!B50 -> 0 | D50: =IF(AND(B50="",C50=""),"",N(C50)-N(B50)) -> 0
A51: =IF(Metas!$B$8="","Meta 3 (aba Metas)","Meta 3: "&Metas!$B$8) -> Meta 3 (aba Metas) | B51: =Set!B51 -> 0 | D51: =IF(AND(B51="",C51=""),"",N(C51)-N(B51)) -> 0
A52: =IF(Metas!$B$9="","Meta 4 (aba Metas)","Meta 4: "&Metas!$B$9) -> Meta 4 (aba Metas) | B52: =Set!B52 -> 0 | D52: =IF(AND(B52="",C52=""),"",N(C52)-N(B52)) -> 0
A53: =IF(Metas!$B$10="","Meta 5 (aba Metas)","Meta 5: "&Metas!$B$10) -> Meta 5 (aba Metas) | B53: =Set!B53 -> 0 | D53: =IF(AND(B53="",C53=""),"",N(C53)-N(B53)) -> 0
A54: Aposentadoria (previdência ou investimentos de longo prazo) | B54: =Set!B54 -> 0 | D54: =IF(AND(B54="",C54=""),"",N(C54)-N(B54)) -> 0
A55: Total do plano | B55: =SUM(B46:B54) -> 1600 | C55: =SUM(C46:C54) -> 0 | D55: =N(C55)-N(B55) -> -1600
A57: SALDO DO MÊS (margem para o plano - plano + entradas não recorrentes) | B57: =N(B43)-B55+N(B9) -> 0 | C57: =IF(N(C8)=0,"",N(C43)-C55+N(C9)) | D57: =N(C57)-N(B57) -> 0 | E57: Negativo: o mês fechou no vermelho. Confira com o extrato.
A59: INDICADORES DO MÊS (realizado)
A60: Taxa de poupança (plano sem seguro ÷ renda total) | C60: =IFERROR((C55-N(C48))/C10,0) -> 0
A61: Necessidades (essenciais + compromissos + provisão) ÷ renda recorrente | C61: =IFERROR((C19+C27+N(C30))/C8,0) -> 0
A62: Desejos (flexíveis) ÷ renda recorrente | C62: =IFERROR(C42/C8,0) -> 0
A63: Plano (dívidas, reserva, metas, aposentadoria) ÷ renda recorrente | C63: =IFERROR(C55/C8,0) -> 0
A64: Referência 50/30/20: 50% necessidades, 30% desejos, 20% plano. É ponto de partida, não regra.

Sheet Nov
A1: ="Orçamento de novembro de "&Início!$C$5 -> Orçamento de novembro de 2026
A2: Previsto: o que você planeja. Realizado: o que aconteceu, pelos extratos e faturas. O previsto vem de outubro; digite por cima se mudar.
A3: Item | B3: Previsto | C3: Realizado | D3: Diferença | E3: Observação
A4: RENDA LÍQUIDA (depois de INSS e IR)
A5: ="Renda líquida de "&Início!$C$6 -> Renda líquida de Paula | B5: =Out!B5 -> 4500 | D5: =IF(AND(B5="",C5=""),"",N(C5)-N(B5)) -> -4500
A6: ="Renda líquida de "&Início!$C$7 -> Renda líquida de Marcos | B6: =Out!B6 -> 3500 | D6: =IF(AND(B6="",C6=""),"",N(C6)-N(B6)) -> -3500
A7: Outras rendas recorrentes (aluguel recebido, pensão) | B7: =Out!B7 -> 0 | D7: =IF(AND(B7="",C7=""),"",N(C7)-N(B7))
A8: Renda recorrente | B8: =SUM(B5:B7) -> 8000 | C8: =SUM(C5:C7) -> 0 | D8: =N(C8)-N(B8) -> -8000
A9: Entradas não recorrentes (13º, bônus, trabalhos avulsos) | B9: =Out!B9 -> 0 | D9: =IF(AND(B9="",C9=""),"",N(C9)-N(B9))
A10: Renda total | B10: =B8+N(B9) -> 8000 | C10: =C8+N(C9) -> 0 | D10: =N(C10)-N(B10) -> -8000
A12: ESSENCIAIS
A13: =Categorias!$C$6 -> Moradia (aluguel ou prestação, condomínio) | B13: =Out!B13 -> 2000 | D13: =IF(AND(B13="",C13=""),"",N(C13)-N(B13)) -> -2000
A14: =Categorias!$C$7 -> Contas da casa (luz, água, gás, internet, celular) | B14: =Out!B14 -> 450 | D14: =IF(AND(B14="",C14=""),"",N(C14)-N(B14)) -> -450
A15: =Categorias!$C$8 -> Alimentação (supermercado e feira) | B15: =Out!B15 -> 1150 | D15: =IF(AND(B15="",C15=""),"",N(C15)-N(B15)) -> -1150
A16: =Categorias!$C$9 -> Transporte (combustível, transporte público, aplicativo) | B16: =Out!B16 -> 350 | D16: =IF(AND(B16="",C16=""),"",N(C16)-N(B16)) -> -350
A17: =Categorias!$C$10 -> Saúde (plano, farmácia, consultas) | B17: =Out!B17 -> 250 | D17: =IF(AND(B17="",C17=""),"",N(C17)-N(B17)) -> -250
A18: =Categorias!$C$11 -> Outros essenciais | B18: =Out!B18 -> 0 | D18: =IF(AND(B18="",C18=""),"",N(C18)-N(B18)) -> 0
A19: Total de essenciais | B19: =SUM(B13:B18) -> 4200 | C19: =SUM(C13:C18) -> 0 | D19: =N(C19)-N(B19) -> -4200
A21: COMPROMISSOS (parcelas e mensalidades com vencimento)
A22: =Categorias!$C$12 -> Financiamento ou empréstimo | B22: =Out!B22 -> 0 | D22: =IF(AND(B22="",C22=""),"",N(C22)-N(B22)) -> 0
A23: =Categorias!$C$13 -> Parcela do carro | B23: =Out!B23 -> 900 | D23: =IF(AND(B23="",C23=""),"",N(C23)-N(B23)) -> -900
A24: =Categorias!$C$14 -> Escola, faculdade e cursos | B24: =Out!B24 -> 400 | D24: =IF(AND(B24="",C24=""),"",N(C24)-N(B24)) -> -400
A25: =Categorias!$C$15 -> Seguros mensais | B25: =Out!B25 -> 0 | D25: =IF(AND(B25="",C25=""),"",N(C25)-N(B25)) -> 0
A26: =Categorias!$C$16 -> Outras parcelas e mensalidades | B26: =Out!B26 -> 0 | D26: =IF(AND(B26="",C26=""),"",N(C26)-N(B26)) -> 0
A27: Total de compromissos | B27: =SUM(B22:B26) -> 1300 | C27: =SUM(C22:C26) -> 0 | D27: =N(C27)-N(B27) -> -1300
A29: DESPESAS IRREGULARES
A30: Provisão mensal (aba Irregulares, total ÷ 12) | B30: =Irregulares!$C$28 -> 500 | C30: =IF(N(C8)=0,"",Irregulares!$C$28) | D30: =N(C30)-N(B30) -> -500
A31: Irregulares pagas neste mês (sai do dinheiro provisionado) | B31: =SUMIF(Irregulares!$D$6:$D$25,11,Irregulares!$C$6:$C$25) -> 0 | D31: =IF(AND(B31="",C31=""),"",N(C31)-N(B31)) -> 0 | E31: Informativo: não entra na margem, que já desconta a provisão.
A33: MARGEM DE DECISÃO (renda recorrente - essenciais - compromissos - provisão) | B33: =B8-B19-B27-N(B30) -> 2000 | C33: =IF(N(C8)=0,"",C8-C19-C27-N(C30)) | D33: =N(C33)-N(B33) -> -2000
A35: FLEXÍVEIS (saem da margem)
A36: =Categorias!$C$17 -> Restaurantes e delivery | B36: =Out!B36 -> 150 | D36: =IF(AND(B36="",C36=""),"",N(C36)-N(B36)) -> -150
A37: =Categorias!$C$18 -> Lazer e passeios | B37: =Out!B37 -> 120 | D37: =IF(AND(B37="",C37=""),"",N(C37)-N(B37)) -> -120
A38: =Categorias!$C$19 -> Compras (roupas, eletrônicos, casa) | B38: =Out!B38 -> 80 | D38: =IF(AND(B38="",C38=""),"",N(C38)-N(B38)) -> -80
A39: =Categorias!$C$20 -> Assinaturas e aplicativos | B39: =Out!B39 -> 50 | D39: =IF(AND(B39="",C39=""),"",N(C39)-N(B39)) -> -50
A40: =Categorias!$C$21 -> Cuidados pessoais | B40: =Out!B40 -> 0 | D40: =IF(AND(B40="",C40=""),"",N(C40)-N(B40)) -> 0
A41: =Categorias!$C$22 -> Presentes e outros | B41: =Out!B41 -> 0 | D41: =IF(AND(B41="",C41=""),"",N(C41)-N(B41)) -> 0
A42: Total de flexíveis | B42: =SUM(B36:B41) -> 400 | C42: =SUM(C36:C41) -> 0 | D42: =N(C42)-N(B42) -> -400
A43: MARGEM PARA O PLANO (margem de decisão - flexíveis) | B43: =N(B33)-B42 -> 1600 | C43: =IF(N(C8)=0,"",N(C33)-C42) | D43: =N(C43)-N(B43) -> -1600
A45: DESTINO DA MARGEM (o seu plano, na ordem do cap. 35)
A46: Pagamento extra de dívidas caras | B46: =Out!B46 -> 0 | D46: =IF(AND(B46="",C46=""),"",N(C46)-N(B46)) -> 0
A47: Reserva de emergência | B47: =Out!B47 -> 1000 | D47: =IF(AND(B47="",C47=""),"",N(C47)-N(B47)) -> -1000
A48: Seguro de vida e proteção | B48: =Out!B48 -> 120 | D48: =IF(AND(B48="",C48=""),"",N(C48)-N(B48)) -> -120
A49: =IF(Metas!$B$6="","Meta 1 (aba Metas)","Meta 1: "&Metas!$B$6) -> Meta 1: Entrada do apartamento | B49: =Out!B49 -> 480 | D49: =IF(AND(B49="",C49=""),"",N(C49)-N(B49)) -> -480
A50: =IF(Metas!$B$7="","Meta 2 (aba Metas)","Meta 2: "&Metas!$B$7) -> Meta 2: Faculdade do filho | B50: =Out!B50 -> 0 | D50: =IF(AND(B50="",C50=""),"",N(C50)-N(B50)) -> 0
A51: =IF(Metas!$B$8="","Meta 3 (aba Metas)","Meta 3: "&Metas!$B$8) -> Meta 3 (aba Metas) | B51: =Out!B51 -> 0 | D51: =IF(AND(B51="",C51=""),"",N(C51)-N(B51)) -> 0
A52: =IF(Metas!$B$9="","Meta 4 (aba Metas)","Meta 4: "&Metas!$B$9) -> Meta 4 (aba Metas) | B52: =Out!B52 -> 0 | D52: =IF(AND(B52="",C52=""),"",N(C52)-N(B52)) -> 0
A53: =IF(Metas!$B$10="","Meta 5 (aba Metas)","Meta 5: "&Metas!$B$10) -> Meta 5 (aba Metas) | B53: =Out!B53 -> 0 | D53: =IF(AND(B53="",C53=""),"",N(C53)-N(B53)) -> 0
A54: Aposentadoria (previdência ou investimentos de longo prazo) | B54: =Out!B54 -> 0 | D54: =IF(AND(B54="",C54=""),"",N(C54)-N(B54)) -> 0
A55: Total do plano | B55: =SUM(B46:B54) -> 1600 | C55: =SUM(C46:C54) -> 0 | D55: =N(C55)-N(B55) -> -1600
A57: SALDO DO MÊS (margem para o plano - plano + entradas não recorrentes) | B57: =N(B43)-B55+N(B9) -> 0 | C57: =IF(N(C8)=0,"",N(C43)-C55+N(C9)) | D57: =N(C57)-N(B57) -> 0 | E57: Negativo: o mês fechou no vermelho. Confira com o extrato.
A59: INDICADORES DO MÊS (realizado)
A60: Taxa de poupança (plano sem seguro ÷ renda total) | C60: =IFERROR((C55-N(C48))/C10,0) -> 0
A61: Necessidades (essenciais + compromissos + provisão) ÷ renda recorrente | C61: =IFERROR((C19+C27+N(C30))/C8,0) -> 0
A62: Desejos (flexíveis) ÷ renda recorrente | C62: =IFERROR(C42/C8,0) -> 0
A63: Plano (dívidas, reserva, metas, aposentadoria) ÷ renda recorrente | C63: =IFERROR(C55/C8,0) -> 0
A64: Referência 50/30/20: 50% necessidades, 30% desejos, 20% plano. É ponto de partida, não regra.

Sheet Dez
A1: ="Orçamento de dezembro de "&Início!$C$5 -> Orçamento de dezembro de 2026
A2: Previsto: o que você planeja. Realizado: o que aconteceu, pelos extratos e faturas. O previsto vem de novembro; digite por cima se mudar.
A3: Item | B3: Previsto | C3: Realizado | D3: Diferença | E3: Observação
A4: RENDA LÍQUIDA (depois de INSS e IR)
A5: ="Renda líquida de "&Início!$C$6 -> Renda líquida de Paula | B5: =Nov!B5 -> 4500 | D5: =IF(AND(B5="",C5=""),"",N(C5)-N(B5)) -> -4500
A6: ="Renda líquida de "&Início!$C$7 -> Renda líquida de Marcos | B6: =Nov!B6 -> 3500 | D6: =IF(AND(B6="",C6=""),"",N(C6)-N(B6)) -> -3500
A7: Outras rendas recorrentes (aluguel recebido, pensão) | B7: =Nov!B7 -> 0 | D7: =IF(AND(B7="",C7=""),"",N(C7)-N(B7))
A8: Renda recorrente | B8: =SUM(B5:B7) -> 8000 | C8: =SUM(C5:C7) -> 0 | D8: =N(C8)-N(B8) -> -8000
A9: Entradas não recorrentes (13º, bônus, trabalhos avulsos) | B9: =Nov!B9 -> 0 | D9: =IF(AND(B9="",C9=""),"",N(C9)-N(B9))
A10: Renda total | B10: =B8+N(B9) -> 8000 | C10: =C8+N(C9) -> 0 | D10: =N(C10)-N(B10) -> -8000
A12: ESSENCIAIS
A13: =Categorias!$C$6 -> Moradia (aluguel ou prestação, condomínio) | B13: =Nov!B13 -> 2000 | D13: =IF(AND(B13="",C13=""),"",N(C13)-N(B13)) -> -2000
A14: =Categorias!$C$7 -> Contas da casa (luz, água, gás, internet, celular) | B14: =Nov!B14 -> 450 | D14: =IF(AND(B14="",C14=""),"",N(C14)-N(B14)) -> -450
A15: =Categorias!$C$8 -> Alimentação (supermercado e feira) | B15: =Nov!B15 -> 1150 | D15: =IF(AND(B15="",C15=""),"",N(C15)-N(B15)) -> -1150
A16: =Categorias!$C$9 -> Transporte (combustível, transporte público, aplicativo) | B16: =Nov!B16 -> 350 | D16: =IF(AND(B16="",C16=""),"",N(C16)-N(B16)) -> -350
A17: =Categorias!$C$10 -> Saúde (plano, farmácia, consultas) | B17: =Nov!B17 -> 250 | D17: =IF(AND(B17="",C17=""),"",N(C17)-N(B17)) -> -250
A18: =Categorias!$C$11 -> Outros essenciais | B18: =Nov!B18 -> 0 | D18: =IF(AND(B18="",C18=""),"",N(C18)-N(B18)) -> 0
A19: Total de essenciais | B19: =SUM(B13:B18) -> 4200 | C19: =SUM(C13:C18) -> 0 | D19: =N(C19)-N(B19) -> -4200
A21: COMPROMISSOS (parcelas e mensalidades com vencimento)
A22: =Categorias!$C$12 -> Financiamento ou empréstimo | B22: =Nov!B22 -> 0 | D22: =IF(AND(B22="",C22=""),"",N(C22)-N(B22)) -> 0
A23: =Categorias!$C$13 -> Parcela do carro | B23: =Nov!B23 -> 900 | D23: =IF(AND(B23="",C23=""),"",N(C23)-N(B23)) -> -900
A24: =Categorias!$C$14 -> Escola, faculdade e cursos | B24: =Nov!B24 -> 400 | D24: =IF(AND(B24="",C24=""),"",N(C24)-N(B24)) -> -400
A25: =Categorias!$C$15 -> Seguros mensais | B25: =Nov!B25 -> 0 | D25: =IF(AND(B25="",C25=""),"",N(C25)-N(B25)) -> 0
A26: =Categorias!$C$16 -> Outras parcelas e mensalidades | B26: =Nov!B26 -> 0 | D26: =IF(AND(B26="",C26=""),"",N(C26)-N(B26)) -> 0
A27: Total de compromissos | B27: =SUM(B22:B26) -> 1300 | C27: =SUM(C22:C26) -> 0 | D27: =N(C27)-N(B27) -> -1300
A29: DESPESAS IRREGULARES
A30: Provisão mensal (aba Irregulares, total ÷ 12) | B30: =Irregulares!$C$28 -> 500 | C30: =IF(N(C8)=0,"",Irregulares!$C$28) | D30: =N(C30)-N(B30) -> -500
A31: Irregulares pagas neste mês (sai do dinheiro provisionado) | B31: =SUMIF(Irregulares!$D$6:$D$25,12,Irregulares!$C$6:$C$25) -> 1200 | D31: =IF(AND(B31="",C31=""),"",N(C31)-N(B31)) -> -1200 | E31: Informativo: não entra na margem, que já desconta a provisão.
A33: MARGEM DE DECISÃO (renda recorrente - essenciais - compromissos - provisão) | B33: =B8-B19-B27-N(B30) -> 2000 | C33: =IF(N(C8)=0,"",C8-C19-C27-N(C30)) | D33: =N(C33)-N(B33) -> -2000
A35: FLEXÍVEIS (saem da margem)
A36: =Categorias!$C$17 -> Restaurantes e delivery | B36: =Nov!B36 -> 150 | D36: =IF(AND(B36="",C36=""),"",N(C36)-N(B36)) -> -150
A37: =Categorias!$C$18 -> Lazer e passeios | B37: =Nov!B37 -> 120 | D37: =IF(AND(B37="",C37=""),"",N(C37)-N(B37)) -> -120
A38: =Categorias!$C$19 -> Compras (roupas, eletrônicos, casa) | B38: =Nov!B38 -> 80 | D38: =IF(AND(B38="",C38=""),"",N(C38)-N(B38)) -> -80
A39: =Categorias!$C$20 -> Assinaturas e aplicativos | B39: =Nov!B39 -> 50 | D39: =IF(AND(B39="",C39=""),"",N(C39)-N(B39)) -> -50
A40: =Categorias!$C$21 -> Cuidados pessoais | B40: =Nov!B40 -> 0 | D40: =IF(AND(B40="",C40=""),"",N(C40)-N(B40)) -> 0
A41: =Categorias!$C$22 -> Presentes e outros | B41: =Nov!B41 -> 0 | D41: =IF(AND(B41="",C41=""),"",N(C41)-N(B41)) -> 0
A42: Total de flexíveis | B42: =SUM(B36:B41) -> 400 | C42: =SUM(C36:C41) -> 0 | D42: =N(C42)-N(B42) -> -400
A43: MARGEM PARA O PLANO (margem de decisão - flexíveis) | B43: =N(B33)-B42 -> 1600 | C43: =IF(N(C8)=0,"",N(C33)-C42) | D43: =N(C43)-N(B43) -> -1600
A45: DESTINO DA MARGEM (o seu plano, na ordem do cap. 35)
A46: Pagamento extra de dívidas caras | B46: =Nov!B46 -> 0 | D46: =IF(AND(B46="",C46=""),"",N(C46)-N(B46)) -> 0
A47: Reserva de emergência | B47: =Nov!B47 -> 1000 | D47: =IF(AND(B47="",C47=""),"",N(C47)-N(B47)) -> -1000
A48: Seguro de vida e proteção | B48: =Nov!B48 -> 120 | D48: =IF(AND(B48="",C48=""),"",N(C48)-N(B48)) -> -120
A49: =IF(Metas!$B$6="","Meta 1 (aba Metas)","Meta 1: "&Metas!$B$6) -> Meta 1: Entrada do apartamento | B49: =Nov!B49 -> 480 | D49: =IF(AND(B49="",C49=""),"",N(C49)-N(B49)) -> -480
A50: =IF(Metas!$B$7="","Meta 2 (aba Metas)","Meta 2: "&Metas!$B$7) -> Meta 2: Faculdade do filho | B50: =Nov!B50 -> 0 | D50: =IF(AND(B50="",C50=""),"",N(C50)-N(B50)) -> 0
A51: =IF(Metas!$B$8="","Meta 3 (aba Metas)","Meta 3: "&Metas!$B$8) -> Meta 3 (aba Metas) | B51: =Nov!B51 -> 0 | D51: =IF(AND(B51="",C51=""),"",N(C51)-N(B51)) -> 0
A52: =IF(Metas!$B$9="","Meta 4 (aba Metas)","Meta 4: "&Metas!$B$9) -> Meta 4 (aba Metas) | B52: =Nov!B52 -> 0 | D52: =IF(AND(B52="",C52=""),"",N(C52)-N(B52)) -> 0
A53: =IF(Metas!$B$10="","Meta 5 (aba Metas)","Meta 5: "&Metas!$B$10) -> Meta 5 (aba Metas) | B53: =Nov!B53 -> 0 | D53: =IF(AND(B53="",C53=""),"",N(C53)-N(B53)) -> 0
A54: Aposentadoria (previdência ou investimentos de longo prazo) | B54: =Nov!B54 -> 0 | D54: =IF(AND(B54="",C54=""),"",N(C54)-N(B54)) -> 0
A55: Total do plano | B55: =SUM(B46:B54) -> 1600 | C55: =SUM(C46:C54) -> 0 | D55: =N(C55)-N(B55) -> -1600
A57: SALDO DO MÊS (margem para o plano - plano + entradas não recorrentes) | B57: =N(B43)-B55+N(B9) -> 0 | C57: =IF(N(C8)=0,"",N(C43)-C55+N(C9)) | D57: =N(C57)-N(B57) -> 0 | E57: Negativo: o mês fechou no vermelho. Confira com o extrato.
A59: INDICADORES DO MÊS (realizado)
A60: Taxa de poupança (plano sem seguro ÷ renda total) | C60: =IFERROR((C55-N(C48))/C10,0) -> 0
A61: Necessidades (essenciais + compromissos + provisão) ÷ renda recorrente | C61: =IFERROR((C19+C27+N(C30))/C8,0) -> 0
A62: Desejos (flexíveis) ÷ renda recorrente | C62: =IFERROR(C42/C8,0) -> 0
A63: Plano (dívidas, reserva, metas, aposentadoria) ÷ renda recorrente | C63: =IFERROR(C55/C8,0) -> 0
A64: Referência 50/30/20: 50% necessidades, 30% desejos, 20% plano. É ponto de partida, não regra.

Sheet Irregulares
B2: Despesas irregulares do ano
B3: Despesas previsíveis que não vêm todo mês. A soma dividida por 12 é a provisão mensal (cap. 3 e cap. 35).
B5: Despesa | C5: Valor no ano | D5: Mês em que vence (1 a 12) | E5: Observação
B6: IPVA e licenciamento | C6: 1800 | D6: 1
B7: Seguro do carro | C7: 2400 | D7: 3
B8: Material escolar e uniforme | C8: 600 | D8: 2
B9: Presentes de fim de ano | C9: 1200 | D9: 12
B27: Total no ano | C27: =SUM(C6:C25) -> 6000
B28: Provisão mensal (total ÷ 12) | C28: =C27/12 -> 500

Sheet Patrimônio
B2: Patrimônio: o que você tem e o que deve
B3: Valores de mercado aproximados. Atualize uma vez por ano, de preferência junto com a declaração do IR.
B5: Item | C5: Tipo | D5: Fim do ano anterior | E5: Hoje | F5: Variação
B6: O QUE VOCÊ TEM
B7: Conta corrente e dinheiro | C7: Liquidez rápida | D7: 1500 | E7: 2000 | F7: =N(E7)-N(D7) -> 500
B8: Reserva de emergência | C8: Liquidez rápida | D8: 4000 | E8: 1000 | F8: =N(E8)-N(D8) -> -3000
B9: Investimentos de resgate rápido | C9: Liquidez rápida | D9: 0 | E9: 0 | F9: =N(E9)-N(D9) -> 0
B10: Investimentos de longo prazo | C10: Longo prazo | D10: 0 | E10: 480 | F10: =N(E10)-N(D10) -> 480
B11: Previdência privada | C11: Longo prazo | D11: 0 | E11: 0 | F11: =N(E11)-N(D11) -> 0
B12: FGTS | C12: Longo prazo | D12: 15000 | E12: 18000 | F12: =N(E12)-N(D12) -> 3000
B13: Imóvel de moradia | C13: Bem de uso | D13: 0 | E13: 0 | F13: =N(E13)-N(D13) -> 0
B14: Outros imóveis | C14: Longo prazo | D14: 0 | E14: 0 | F14: =N(E14)-N(D14) -> 0
B15: Veículos | C15: Bem de uso | D15: 50000 | E15: 45000 | F15: =N(E15)-N(D15) -> -5000
B16: Participação em empresa | C16: Empresa | D16: 0 | E16: 0 | F16: =N(E16)-N(D16) -> 0
B17: Outros bens | C17: Bem de uso | D17: 0 | E17: 0 | F17: =N(E17)-N(D17) -> 0
B18: Total do que você tem | D18: =SUM(D7:D17) -> 70500 | E18: =SUM(E7:E17) -> 66480 | F18: =SUM(F7:F17) -> -4020
B20: O QUE VOCÊ DEVE (saldo devedor)
B21: Financiamento imobiliário | C21: Dívida | D21: 0 | E21: 0 | F21: =N(E21)-N(D21) -> 0
B22: Financiamento de veículo | C22: Dívida | D22: 25000 | E22: 20000 | F22: =N(E22)-N(D22) -> -5000
B23: Empréstimos e consignado | C23: Dívida | D23: 0 | E23: 0 | F23: =N(E23)-N(D23) -> 0
B24: Cartão de crédito (rotativo e parcelas) | C24: Dívida | D24: 3000 | E24: 0 | F24: =N(E24)-N(D24) -> -3000
B25: Cheque especial | C25: Dívida | D25: 0 | E25: 0 | F25: =N(E25)-N(D25) -> 0
B26: Outras dívidas | C26: Dívida | D26: 0 | E26: 0 | F26: =N(E26)-N(D26) -> 0
B27: Total do que você deve | D27: =SUM(D21:D26) -> 28000 | E27: =SUM(E21:E26) -> 20000 | F27: =SUM(F21:F26) -> -8000
B28: Conferência: saldo total na aba Dívidas | E28: =Dívidas!$D$27 -> 23000
B30: PATRIMÔNIO LÍQUIDO (tem - deve) | D30: =D18-D27 -> 42500 | E30: =E18-E27 -> 46480 | F30: =F18-F27 -> 3980
B32: Avais e garantias dadas a terceiros ou à sua empresa (fora do total) | E32: 0
B34: INDICADORES
B35: Meses de reserva (liquidez rápida ÷ essenciais e compromissos médios do mês) | E35: =IFERROR(SUMIF(C7:C17,"Liquidez rápida",E7:E17)/(Resumo!$O$9+Resumo!$O$10),0) -> 0.54678007
B36: Concentração na empresa (empresa ÷ total do que tem) | E36: =IFERROR(SUMIF(C7:C17,"Empresa",E7:E17)/E18,0) -> 0
B37: Dívidas ÷ total do que tem | E37: =IFERROR(E27/E18,0) -> 0.30084236
B38: Avais ÷ patrimônio líquido | E38: =IFERROR(E32/E30,0) -> 0
B40: Reserva: cap. 8 e calculadora de reserva de emergência. Empresa e avais: cap. 27, cap. 28 e guia de patrimônio da família e do negócio.

Sheet Dívidas
B2: Dívidas: saldo, juros e ordem de quitação
B3: Avalanche: paga primeiro a de juros mais altos (economiza mais). Bola de neve: paga primeiro a de menor saldo (motiva mais). Cap. 24.
B5: Credor | C5: Tipo | D5: Saldo devedor | E5: Parcela mensal | F5: Juros ao mês | G5: Juros ao ano | H5: Parcelas restantes | I5: Em atraso? | J5: Ordem avalanche | K5: Ordem bola de neve
B6: Cartão (rotativo) | C6: Cartão de crédito | D6: 3000 | E6: 300 | F6: 0.12 | G6: =IF(F6="","",(1+F6)^12-1) -> 2.895976 | H6: 0 | I6: Não | J6: =IF(OR(D6="",N(D6)=0,F6=""),"",COUNTIFS($F$6:$F$25,">"&F6,$D$6:$D$25,">0")+1) -> 1 | K6: =IF(OR(D6="",N(D6)=0),"",COUNTIFS($D$6:$D$25,"<"&D6,$D$6:$D$25,">0")+1) -> 1
B7: Financiamento do carro | C7: Financiamento | D7: 20000 | E7: 900 | F7: 0.018 | G7: =IF(F7="","",(1+F7)^12-1) -> 0.23872053 | H7: 28 | I7: Não | J7: =IF(OR(D7="",N(D7)=0,F7=""),"",COUNTIFS($F$6:$F$25,">"&F7,$D$6:$D$25,">0")+1) -> 2 | K7: =IF(OR(D7="",N(D7)=0),"",COUNTIFS($D$6:$D$25,"<"&D7,$D$6:$D$25,">0")+1) -> 2
G8: =IF(F8="","",(1+F8)^12-1) | J8: =IF(OR(D8="",N(D8)=0,F8=""),"",COUNTIFS($F$6:$F$25,">"&F8,$D$6:$D$25,">0")+1) | K8: =IF(OR(D8="",N(D8)=0),"",COUNTIFS($D$6:$D$25,"<"&D8,$D$6:$D$25,">0")+1)
G9: =IF(F9="","",(1+F9)^12-1) | J9: =IF(OR(D9="",N(D9)=0,F9=""),"",COUNTIFS($F$6:$F$25,">"&F9,$D$6:$D$25,">0")+1) | K9: =IF(OR(D9="",N(D9)=0),"",COUNTIFS($D$6:$D$25,"<"&D9,$D$6:$D$25,">0")+1)
G10: =IF(F10="","",(1+F10)^12-1) | J10: =IF(OR(D10="",N(D10)=0,F10=""),"",COUNTIFS($F$6:$F$25,">"&F10,$D$6:$D$25,">0")+1) | K10: =IF(OR(D10="",N(D10)=0),"",COUNTIFS($D$6:$D$25,"<"&D10,$D$6:$D$25,">0")+1)
G11: =IF(F11="","",(1+F11)^12-1) | J11: =IF(OR(D11="",N(D11)=0,F11=""),"",COUNTIFS($F$6:$F$25,">"&F11,$D$6:$D$25,">0")+1) | K11: =IF(OR(D11="",N(D11)=0),"",COUNTIFS($D$6:$D$25,"<"&D11,$D$6:$D$25,">0")+1)
G12: =IF(F12="","",(1+F12)^12-1) | J12: =IF(OR(D12="",N(D12)=0,F12=""),"",COUNTIFS($F$6:$F$25,">"&F12,$D$6:$D$25,">0")+1) | K12: =IF(OR(D12="",N(D12)=0),"",COUNTIFS($D$6:$D$25,"<"&D12,$D$6:$D$25,">0")+1)
G13: =IF(F13="","",(1+F13)^12-1) | J13: =IF(OR(D13="",N(D13)=0,F13=""),"",COUNTIFS($F$6:$F$25,">"&F13,$D$6:$D$25,">0")+1) | K13: =IF(OR(D13="",N(D13)=0),"",COUNTIFS($D$6:$D$25,"<"&D13,$D$6:$D$25,">0")+1)
G14: =IF(F14="","",(1+F14)^12-1) | J14: =IF(OR(D14="",N(D14)=0,F14=""),"",COUNTIFS($F$6:$F$25,">"&F14,$D$6:$D$25,">0")+1) | K14: =IF(OR(D14="",N(D14)=0),"",COUNTIFS($D$6:$D$25,"<"&D14,$D$6:$D$25,">0")+1)
G15: =IF(F15="","",(1+F15)^12-1) | J15: =IF(OR(D15="",N(D15)=0,F15=""),"",COUNTIFS($F$6:$F$25,">"&F15,$D$6:$D$25,">0")+1) | K15: =IF(OR(D15="",N(D15)=0),"",COUNTIFS($D$6:$D$25,"<"&D15,$D$6:$D$25,">0")+1)
G16: =IF(F16="","",(1+F16)^12-1) | J16: =IF(OR(D16="",N(D16)=0,F16=""),"",COUNTIFS($F$6:$F$25,">"&F16,$D$6:$D$25,">0")+1) | K16: =IF(OR(D16="",N(D16)=0),"",COUNTIFS($D$6:$D$25,"<"&D16,$D$6:$D$25,">0")+1)
G17: =IF(F17="","",(1+F17)^12-1) | J17: =IF(OR(D17="",N(D17)=0,F17=""),"",COUNTIFS($F$6:$F$25,">"&F17,$D$6:$D$25,">0")+1) | K17: =IF(OR(D17="",N(D17)=0),"",COUNTIFS($D$6:$D$25,"<"&D17,$D$6:$D$25,">0")+1)
G18: =IF(F18="","",(1+F18)^12-1) | J18: =IF(OR(D18="",N(D18)=0,F18=""),"",COUNTIFS($F$6:$F$25,">"&F18,$D$6:$D$25,">0")+1) | K18: =IF(OR(D18="",N(D18)=0),"",COUNTIFS($D$6:$D$25,"<"&D18,$D$6:$D$25,">0")+1)
G19: =IF(F19="","",(1+F19)^12-1) | J19: =IF(OR(D19="",N(D19)=0,F19=""),"",COUNTIFS($F$6:$F$25,">"&F19,$D$6:$D$25,">0")+1) | K19: =IF(OR(D19="",N(D19)=0),"",COUNTIFS($D$6:$D$25,"<"&D19,$D$6:$D$25,">0")+1)
... G25: =IF(F25="","",(1+F25)^12-1) | J25: =IF(OR(D25="",N(D25)=0,F25=""),"",COUNTIFS($F$6:$F$25,">"&F25,$D$6:$D$25,">0")+1) | K25: =IF(OR(D25="",N(D25)=0),"",COUNTIFS($D$6:$D$25,"<"&D25,$D$6:$D$25,">0")+1)
B27: Totais | D27: =SUM(D6:D25) -> 23000 | E27: =SUM(E6:E25) -> 1200
B28: Parcelas ÷ renda recorrente média | E28: =IFERROR(E27/Resumo!$O$7,0) -> 0.15
B30: Juros ao mês: veja no contrato, na fatura ou no Registrato do Banco Central. Simule a quitação na calculadora bola de neve x avalanche do blog.

Sheet Metas
B2: Metas: finalidade, valor e data
B3: Valores em reais de hoje. O rendimento é o esperado acima da inflação (hipótese sua, não promessa). Cap. 2 e cap. 35.
B5: Finalidade | C5: Valor (R$ de hoje) | D5: Data alvo | E5: Já guardado | F5: Rendimento real ao ano | G5: Meses até a data | H5: Depósito mensal necessário | I5: Depósito mensal planejado | J5: % atingido | K5: Onde guardar (prazo e risco) | L5: Prioridade
B6: Entrada do apartamento | C6: 80000 | D6: 47848 | E6: 0 | F6: 0.04 | G6: =IF(D6="","",MAX(0,(YEAR(D6)-YEAR(TODAY()))*12+MONTH(D6)-MONTH(TODAY()))) -> 50 | H6: =IF(OR(B6="",C6="",G6=""),"",IF(G6=0,MAX(0,C6-E6),MAX(0,PMT((1+F6)^(1/12)-1,G6,E6,-C6)))) -> 1475.233 | I6: 480 | J6: =IF(OR(C6="",C6=0),"",MIN(1,E6/C6)) -> 0 | K6: Vencimento perto da data da compra | L6: 2
B7: Faculdade do filho | C7: 100000 | D7: 51166 | E7: 0 | F7: 0.04 | G7: =IF(D7="","",MAX(0,(YEAR(D7)-YEAR(TODAY()))*12+MONTH(D7)-MONTH(TODAY()))) -> 159 | H7: =IF(OR(B7="",C7="",G7=""),"",IF(G7=0,MAX(0,C7-E7),MAX(0,PMT((1+F7)^(1/12)-1,G7,E7,-C7)))) -> 480.38667 | I7: 0 | J7: =IF(OR(C7="",C7=0),"",MIN(1,E7/C7)) -> 0 | K7: Longo prazo, conforme o perfil | L7: 3
G8: =IF(D8="","",MAX(0,(YEAR(D8)-YEAR(TODAY()))*12+MONTH(D8)-MONTH(TODAY()))) | H8: =IF(OR(B8="",C8="",G8=""),"",IF(G8=0,MAX(0,C8-E8),MAX(0,PMT((1+F8)^(1/12)-1,G8,E8,-C8)))) | J8: =IF(OR(C8="",C8=0),"",MIN(1,E8/C8))
G9: =IF(D9="","",MAX(0,(YEAR(D9)-YEAR(TODAY()))*12+MONTH(D9)-MONTH(TODAY()))) | H9: =IF(OR(B9="",C9="",G9=""),"",IF(G9=0,MAX(0,C9-E9),MAX(0,PMT((1+F9)^(1/12)-1,G9,E9,-C9)))) | J9: =IF(OR(C9="",C9=0),"",MIN(1,E9/C9))
G10: =IF(D10="","",MAX(0,(YEAR(D10)-YEAR(TODAY()))*12+MONTH(D10)-MONTH(TODAY()))) | H10: =IF(OR(B10="",C10="",G10=""),"",IF(G10=0,MAX(0,C10-E10),MAX(0,PMT((1+F10)^(1/12)-1,G10,E10,-C10)))) | J10: =IF(OR(C10="",C10=0),"",MIN(1,E10/C10))
B12: Totais | H12: =SUM(H6:H10) -> 1955.6197 | I12: =SUM(I6:I10) -> 480
B14: Sobra média para metas (margem para o plano menos dívidas, reserva, seguro e aposentadoria; aba Resumo) | H14: =Resumo!O15-Resumo!O18-Resumo!O19-Resumo!O20-Resumo!O21 -> 486.66667
B15: Os depósitos planejados cabem na margem? | H15: =IF(H14=0,"Preencha os meses",IF(I12<=H14,"Sim","Não: reveja valor, data ou ordem")) -> Sim
B17: Como a conta é feita: depósito = PMT(taxa mensal; meses; já guardado; -valor), com taxa mensal = (1 + rendimento real)^(1/12) - 1. Sem rendimento informado, a conta usa 0%. A mesma conta está na calculadora de meta financeira do blog.

Sheet Revisão
B2: Revisão anual e gatilhos de revisão
B3: Uma vez por ano, e sempre que a vida mudar (cap. 35, etapa 6).
B5: Item | C5: Feito? | D5: Data | E5: Anotações
B6: Refazer o retrato: três meses de extratos e faturas
B7: Atualizar as despesas irregulares do ano
B8: Atualizar a aba Patrimônio e comparar com o ano anterior
B9: Rever as dívidas e a ordem de quitação
B10: Conferir se a reserva cobre os meses combinados
B11: Atualizar as metas pela inflação (calculadora de inflação do blog)
B12: Rebalancear os investimentos conforme o perfil (cap. 5)
B13: Conferir seguros e beneficiários de seguros e previdência (caps. 20, 32 e 34)
B14: Conferir testamento e pasta da família (cap. 34)
B15: Aproveitar a declaração do IR para revisar deduções (cap. 33)
B16: Conferir os valores do ano na página Os números do ano
B17: Marcar a data da próxima revisão (aba Plano)
... B28: Mudança de regra: imposto, INSS ou juros (Os números do ano)

Sheet Categorias
B2: Nomes das categorias
B3: Troque os nomes aqui; eles mudam sozinhos nas 12 abas de mês.
B5: Grupo | C5: Categoria
B6: Essenciais | C6: Moradia (aluguel ou prestação, condomínio)
B7: Essenciais | C7: Contas da casa (luz, água, gás, internet, celular)
B8: Essenciais | C8: Alimentação (supermercado e feira)
B9: Essenciais | C9: Transporte (combustível, transporte público, aplicativo)
B10: Essenciais | C10: Saúde (plano, farmácia, consultas)
B11: Essenciais | C11: Outros essenciais
B12: Compromissos | C12: Financiamento ou empréstimo
B13: Compromissos | C13: Parcela do carro
B14: Compromissos | C14: Escola, faculdade e cursos
B15: Compromissos | C15: Seguros mensais
B16: Compromissos | C16: Outras parcelas e mensalidades
... B22: Flexíveis | C22: Presentes e outros
